{"version":"0.4","title":"sorry netflix","type":"page","content":[{"id":"3d5c37b9","settings":{"content_width":{"unit":"px","size":752},"background_background":"gradient","background_color":"#0c0003","background_color_b":"#0c0204","background_gradient_angle":{"unit":"deg","size":0},"background_overlay_background":"classic","background_overlay_color":"#ebb0e7","background_overlay_color_b":"#2642d3","background_overlay_gradient_angle":{"unit":"deg","size":260},"background_overlay_image":{"id":"16","url":"http:\/\/vbucks-free-generator.com\/wp-content\/uploads\/2018\/10\/Background-Digital.jpg"},"background_overlay_position":"top center","background_overlay_attachment":"fixed","background_overlay_opacity":{"unit":"px","size":0.03},"css_filters_blur":{"unit":"px","size":3.3},"overlay_blend_mode":"luminosity","border_width":{"unit":"px","top":"0","right":"30","bottom":"0","left":"30","isLinked":false},"border_color":"#ffffff","shape_divider_bottom_color":"#f4f4f4","margin":{"unit":"px","top":"-9","right":0,"bottom":"66","left":0,"isLinked":false},"padding":{"unit":"px","top":"71","right":"0","bottom":"30","left":"0","isLinked":false},"background_overlay_repeat":"no-repeat","background_overlay_size":"cover","border_radius":{"unit":"px","top":"010","right":"010","bottom":"0","left":"0","isLinked":false},"padding_tablet":{"unit":"px","top":"50","right":"40","bottom":"50","left":"40","isLinked":false},"padding_mobile":{"unit":"px","top":"40","right":"20","bottom":"40","left":"20","isLinked":false},"background_color_stop":{"unit":"%","size":52},"background_color_b_stop":{"unit":"%","size":0},"custom_height":{"unit":"px","size":400,"sizes":[]},"custom_height_tablet":{"unit":"px","size":"","sizes":[]},"custom_height_mobile":{"unit":"px","size":"","sizes":[]},"background_xpos":{"unit":"px","size":0,"sizes":[]},"background_xpos_tablet":{"unit":"px","size":0,"sizes":[]},"background_xpos_mobile":{"unit":"px","size":0,"sizes":[]},"background_ypos":{"unit":"px","size":0,"sizes":[]},"background_ypos_tablet":{"unit":"px","size":0,"sizes":[]},"background_ypos_mobile":{"unit":"px","size":0,"sizes":[]},"background_bg_width":{"unit":"%","size":100,"sizes":[]},"background_bg_width_tablet":{"unit":"px","size":"","sizes":[]},"background_bg_width_mobile":{"unit":"px","size":"","sizes":[]},"background_hover_color_stop":{"unit":"%","size":0,"sizes":[]},"background_hover_color_b_stop":{"unit":"%","size":100,"sizes":[]},"background_hover_gradient_angle":{"unit":"deg","size":180,"sizes":[]},"background_hover_xpos":{"unit":"px","size":0,"sizes":[]},"background_hover_xpos_tablet":{"unit":"px","size":0,"sizes":[]},"background_hover_xpos_mobile":{"unit":"px","size":0,"sizes":[]},"background_hover_ypos":{"unit":"px","size":0,"sizes":[]},"background_hover_ypos_tablet":{"unit":"px","size":0,"sizes":[]},"background_hover_ypos_mobile":{"unit":"px","size":0,"sizes":[]},"background_hover_bg_width":{"unit":"%","size":100,"sizes":[]},"background_hover_bg_width_tablet":{"unit":"px","size":"","sizes":[]},"background_hover_bg_width_mobile":{"unit":"px","size":"","sizes":[]},"background_hover_transition":{"unit":"px","size":0.3,"sizes":[]},"background_overlay_color_stop":{"unit":"%","size":0,"sizes":[]},"background_overlay_color_b_stop":{"unit":"%","size":100,"sizes":[]},"background_overlay_xpos":{"unit":"px","size":0,"sizes":[]},"background_overlay_xpos_tablet":{"unit":"px","size":0,"sizes":[]},"background_overlay_xpos_mobile":{"unit":"px","size":0,"sizes":[]},"background_overlay_ypos":{"unit":"px","size":0,"sizes":[]},"background_overlay_ypos_tablet":{"unit":"px","size":0,"sizes":[]},"background_overlay_ypos_mobile":{"unit":"px","size":0,"sizes":[]},"background_overlay_bg_width":{"unit":"%","size":100,"sizes":[]},"background_overlay_bg_width_tablet":{"unit":"px","size":"","sizes":[]},"background_overlay_bg_width_mobile":{"unit":"px","size":"","sizes":[]},"css_filters_brightness":{"unit":"px","size":100,"sizes":[]},"css_filters_contrast":{"unit":"px","size":100,"sizes":[]},"css_filters_saturate":{"unit":"px","size":100,"sizes":[]},"css_filters_hue":{"unit":"px","size":0,"sizes":[]},"background_overlay_hover_color_stop":{"unit":"%","size":0,"sizes":[]},"background_overlay_hover_color_b_stop":{"unit":"%","size":100,"sizes":[]},"background_overlay_hover_gradient_angle":{"unit":"deg","size":180,"sizes":[]},"background_overlay_hover_xpos":{"unit":"px","size":0,"sizes":[]},"background_overlay_hover_xpos_tablet":{"unit":"px","size":0,"sizes":[]},"background_overlay_hover_xpos_mobile":{"unit":"px","size":0,"sizes":[]},"background_overlay_hover_ypos":{"unit":"px","size":0,"sizes":[]},"background_overlay_hover_ypos_tablet":{"unit":"px","size":0,"sizes":[]},"background_overlay_hover_ypos_mobile":{"unit":"px","size":0,"sizes":[]},"background_overlay_hover_bg_width":{"unit":"%","size":100,"sizes":[]},"background_overlay_hover_bg_width_tablet":{"unit":"px","size":"","sizes":[]},"background_overlay_hover_bg_width_mobile":{"unit":"px","size":"","sizes":[]},"background_overlay_hover_opacity":{"unit":"px","size":0.5,"sizes":[]},"css_filters_hover_blur":{"unit":"px","size":0,"sizes":[]},"css_filters_hover_brightness":{"unit":"px","size":100,"sizes":[]},"css_filters_hover_contrast":{"unit":"px","size":100,"sizes":[]},"css_filters_hover_saturate":{"unit":"px","size":100,"sizes":[]},"css_filters_hover_hue":{"unit":"px","size":0,"sizes":[]},"background_overlay_hover_transition":{"unit":"px","size":0.3,"sizes":[]},"border_hover_transition":{"unit":"px","size":0.3,"sizes":[]},"shape_divider_top_width":{"unit":"%","size":"","sizes":[]},"shape_divider_top_width_tablet":{"unit":"%","size":"","sizes":[]},"shape_divider_top_width_mobile":{"unit":"%","size":"","sizes":[]},"shape_divider_top_height":{"unit":"px","size":"","sizes":[]},"shape_divider_top_height_tablet":{"unit":"px","size":"","sizes":[]},"shape_divider_top_height_mobile":{"unit":"px","size":"","sizes":[]},"shape_divider_bottom_width":{"unit":"%","size":"","sizes":[]},"shape_divider_bottom_width_tablet":{"unit":"%","size":"","sizes":[]},"shape_divider_bottom_width_mobile":{"unit":"%","size":"","sizes":[]},"shape_divider_bottom_height":{"unit":"px","size":"","sizes":[]},"shape_divider_bottom_height_tablet":{"unit":"px","size":"","sizes":[]},"shape_divider_bottom_height_mobile":{"unit":"px","size":"","sizes":[]}},"elements":[{"id":"1b6750c3","settings":{"_column_size":100,"space_between_widgets":30,"background_color_stop":{"unit":"%","size":0,"sizes":[]},"background_color_b_stop":{"unit":"%","size":100,"sizes":[]},"background_gradient_angle":{"unit":"deg","size":180,"sizes":[]},"background_xpos":{"unit":"px","size":0,"sizes":[]},"background_xpos_tablet":{"unit":"px","size":0,"sizes":[]},"background_xpos_mobile":{"unit":"px","size":0,"sizes":[]},"background_ypos":{"unit":"px","size":0,"sizes":[]},"background_ypos_tablet":{"unit":"px","size":0,"sizes":[]},"background_ypos_mobile":{"unit":"px","size":0,"sizes":[]},"background_bg_width":{"unit":"%","size":100,"sizes":[]},"background_bg_width_tablet":{"unit":"px","size":"","sizes":[]},"background_bg_width_mobile":{"unit":"px","size":"","sizes":[]},"background_hover_color_stop":{"unit":"%","size":0,"sizes":[]},"background_hover_color_b_stop":{"unit":"%","size":100,"sizes":[]},"background_hover_gradient_angle":{"unit":"deg","size":180,"sizes":[]},"background_hover_xpos":{"unit":"px","size":0,"sizes":[]},"background_hover_xpos_tablet":{"unit":"px","size":0,"sizes":[]},"background_hover_xpos_mobile":{"unit":"px","size":0,"sizes":[]},"background_hover_ypos":{"unit":"px","size":0,"sizes":[]},"background_hover_ypos_tablet":{"unit":"px","size":0,"sizes":[]},"background_hover_ypos_mobile":{"unit":"px","size":0,"sizes":[]},"background_hover_bg_width":{"unit":"%","size":100,"sizes":[]},"background_hover_bg_width_tablet":{"unit":"px","size":"","sizes":[]},"background_hover_bg_width_mobile":{"unit":"px","size":"","sizes":[]},"background_hover_transition":{"unit":"px","size":0.3,"sizes":[]},"background_overlay_color_stop":{"unit":"%","size":0,"sizes":[]},"background_overlay_color_b_stop":{"unit":"%","size":100,"sizes":[]},"background_overlay_gradient_angle":{"unit":"deg","size":180,"sizes":[]},"background_overlay_xpos":{"unit":"px","size":0,"sizes":[]},"background_overlay_xpos_tablet":{"unit":"px","size":0,"sizes":[]},"background_overlay_xpos_mobile":{"unit":"px","size":0,"sizes":[]},"background_overlay_ypos":{"unit":"px","size":0,"sizes":[]},"background_overlay_ypos_tablet":{"unit":"px","size":0,"sizes":[]},"background_overlay_ypos_mobile":{"unit":"px","size":0,"sizes":[]},"background_overlay_bg_width":{"unit":"%","size":100,"sizes":[]},"background_overlay_bg_width_tablet":{"unit":"px","size":"","sizes":[]},"background_overlay_bg_width_mobile":{"unit":"px","size":"","sizes":[]},"background_overlay_opacity":{"unit":"px","size":0.5,"sizes":[]},"css_filters_blur":{"unit":"px","size":0,"sizes":[]},"css_filters_brightness":{"unit":"px","size":100,"sizes":[]},"css_filters_contrast":{"unit":"px","size":100,"sizes":[]},"css_filters_saturate":{"unit":"px","size":100,"sizes":[]},"css_filters_hue":{"unit":"px","size":0,"sizes":[]},"background_overlay_hover_color_stop":{"unit":"%","size":0,"sizes":[]},"background_overlay_hover_color_b_stop":{"unit":"%","size":100,"sizes":[]},"background_overlay_hover_gradient_angle":{"unit":"deg","size":180,"sizes":[]},"background_overlay_hover_xpos":{"unit":"px","size":0,"sizes":[]},"background_overlay_hover_xpos_tablet":{"unit":"px","size":0,"sizes":[]},"background_overlay_hover_xpos_mobile":{"unit":"px","size":0,"sizes":[]},"background_overlay_hover_ypos":{"unit":"px","size":0,"sizes":[]},"background_overlay_hover_ypos_tablet":{"unit":"px","size":0,"sizes":[]},"background_overlay_hover_ypos_mobile":{"unit":"px","size":0,"sizes":[]},"background_overlay_hover_bg_width":{"unit":"%","size":100,"sizes":[]},"background_overlay_hover_bg_width_tablet":{"unit":"px","size":"","sizes":[]},"background_overlay_hover_bg_width_mobile":{"unit":"px","size":"","sizes":[]},"background_overlay_hover_opacity":{"unit":"px","size":0.5,"sizes":[]},"css_filters_hover_blur":{"unit":"px","size":0,"sizes":[]},"css_filters_hover_brightness":{"unit":"px","size":100,"sizes":[]},"css_filters_hover_contrast":{"unit":"px","size":100,"sizes":[]},"css_filters_hover_saturate":{"unit":"px","size":100,"sizes":[]},"css_filters_hover_hue":{"unit":"px","size":0,"sizes":[]},"background_overlay_hover_transition":{"unit":"px","size":0.3,"sizes":[]},"border_hover_transition":{"unit":"px","size":0.3,"sizes":[]}},"elements":[{"id":"56243680","settings":{"title":"<b>Too Late :\/<\/b>","typography_typography":"custom","typography_font_size":{"unit":"px","size":50},"typography_font_weight":"300","typography_line_height":{"unit":"em","size":1.1},"align":"center","title_color":"#ffffff","typography_text_transform":"capitalize","text_shadow_text_shadow_type":"yes","text_shadow_text_shadow":{"horizontal":10,"vertical":10,"blur":20,"color":"rgba(0,0,0,0.11)"},"typography_font_family":"Montserrat","typography_font_size_tablet":{"unit":"px","size":"","sizes":[]},"typography_font_size_mobile":{"unit":"px","size":"","sizes":[]},"typography_line_height_tablet":{"unit":"em","size":"","sizes":[]},"typography_line_height_mobile":{"unit":"em","size":"","sizes":[]},"typography_letter_spacing":{"unit":"px","size":"","sizes":[]},"typography_letter_spacing_tablet":{"unit":"px","size":"","sizes":[]},"typography_letter_spacing_mobile":{"unit":"px","size":"","sizes":[]},"_background_color_stop":{"unit":"%","size":0,"sizes":[]},"_background_color_b_stop":{"unit":"%","size":100,"sizes":[]},"_background_gradient_angle":{"unit":"deg","size":180,"sizes":[]},"_background_xpos":{"unit":"px","size":0,"sizes":[]},"_background_xpos_tablet":{"unit":"px","size":0,"sizes":[]},"_background_xpos_mobile":{"unit":"px","size":0,"sizes":[]},"_background_ypos":{"unit":"px","size":0,"sizes":[]},"_background_ypos_tablet":{"unit":"px","size":0,"sizes":[]},"_background_ypos_mobile":{"unit":"px","size":0,"sizes":[]},"_background_bg_width":{"unit":"%","size":100,"sizes":[]},"_background_bg_width_tablet":{"unit":"px","size":"","sizes":[]},"_background_bg_width_mobile":{"unit":"px","size":"","sizes":[]},"_background_hover_color_stop":{"unit":"%","size":0,"sizes":[]},"_background_hover_color_b_stop":{"unit":"%","size":100,"sizes":[]},"_background_hover_gradient_angle":{"unit":"deg","size":180,"sizes":[]},"_background_hover_xpos":{"unit":"px","size":0,"sizes":[]},"_background_hover_xpos_tablet":{"unit":"px","size":0,"sizes":[]},"_background_hover_xpos_mobile":{"unit":"px","size":0,"sizes":[]},"_background_hover_ypos":{"unit":"px","size":0,"sizes":[]},"_background_hover_ypos_tablet":{"unit":"px","size":0,"sizes":[]},"_background_hover_ypos_mobile":{"unit":"px","size":0,"sizes":[]},"_background_hover_bg_width":{"unit":"%","size":100,"sizes":[]},"_background_hover_bg_width_tablet":{"unit":"px","size":"","sizes":[]},"_background_hover_bg_width_mobile":{"unit":"px","size":"","sizes":[]},"_background_hover_transition":{"unit":"px","size":"","sizes":[]},"_border_hover_transition":{"unit":"px","size":"","sizes":[]},"_element_custom_width":{"unit":"px","size":"","sizes":[]},"_element_custom_width_tablet":{"unit":"px","size":"","sizes":[]},"_element_custom_width_mobile":{"unit":"px","size":"","sizes":[]},"_offset_x":{"unit":"px","size":"0","sizes":[]},"_offset_x_tablet":{"unit":"px","size":"","sizes":[]},"_offset_x_mobile":{"unit":"px","size":"","sizes":[]},"_offset_x_end":{"unit":"px","size":"0","sizes":[]},"_offset_x_end_tablet":{"unit":"px","size":"","sizes":[]},"_offset_x_end_mobile":{"unit":"px","size":"","sizes":[]},"_offset_y":{"unit":"px","size":"0","sizes":[]},"_offset_y_tablet":{"unit":"px","size":"","sizes":[]},"_offset_y_mobile":{"unit":"px","size":"","sizes":[]},"_offset_y_end":{"unit":"px","size":"0","sizes":[]},"_offset_y_end_tablet":{"unit":"px","size":"","sizes":[]},"_offset_y_end_mobile":{"unit":"px","size":"","sizes":[]}},"elements":[],"isInner":false,"widgetType":"heading","elType":"widget"},{"id":"6d8da64","settings":{"alert_title":"Sorry :'(","alert_description":"As you know our NETFLIX Generator is available for just the first 100 users per day.\nToday we reached our limit.<br>Please try again tomorrow or signup to be the first one!","border_left-width":{"unit":"px","size":"","sizes":[]},"alert_title_font_size":{"unit":"px","size":"","sizes":[]},"alert_title_font_size_tablet":{"unit":"px","size":"","sizes":[]},"alert_title_font_size_mobile":{"unit":"px","size":"","sizes":[]},"alert_title_line_height":{"unit":"em","size":"","sizes":[]},"alert_title_line_height_tablet":{"unit":"em","size":"","sizes":[]},"alert_title_line_height_mobile":{"unit":"em","size":"","sizes":[]},"alert_title_letter_spacing":{"unit":"px","size":"","sizes":[]},"alert_title_letter_spacing_tablet":{"unit":"px","size":"","sizes":[]},"alert_title_letter_spacing_mobile":{"unit":"px","size":"","sizes":[]},"alert_description_font_size":{"unit":"px","size":"","sizes":[]},"alert_description_font_size_tablet":{"unit":"px","size":"","sizes":[]},"alert_description_font_size_mobile":{"unit":"px","size":"","sizes":[]},"alert_description_line_height":{"unit":"em","size":"","sizes":[]},"alert_description_line_height_tablet":{"unit":"em","size":"","sizes":[]},"alert_description_line_height_mobile":{"unit":"em","size":"","sizes":[]},"alert_description_letter_spacing":{"unit":"px","size":"","sizes":[]},"alert_description_letter_spacing_tablet":{"unit":"px","size":"","sizes":[]},"alert_description_letter_spacing_mobile":{"unit":"px","size":"","sizes":[]},"_background_color_stop":{"unit":"%","size":0,"sizes":[]},"_background_color_b_stop":{"unit":"%","size":100,"sizes":[]},"_background_gradient_angle":{"unit":"deg","size":180,"sizes":[]},"_background_xpos":{"unit":"px","size":0,"sizes":[]},"_background_xpos_tablet":{"unit":"px","size":0,"sizes":[]},"_background_xpos_mobile":{"unit":"px","size":0,"sizes":[]},"_background_ypos":{"unit":"px","size":0,"sizes":[]},"_background_ypos_tablet":{"unit":"px","size":0,"sizes":[]},"_background_ypos_mobile":{"unit":"px","size":0,"sizes":[]},"_background_bg_width":{"unit":"%","size":100,"sizes":[]},"_background_bg_width_tablet":{"unit":"px","size":"","sizes":[]},"_background_bg_width_mobile":{"unit":"px","size":"","sizes":[]},"_background_hover_color_stop":{"unit":"%","size":0,"sizes":[]},"_background_hover_color_b_stop":{"unit":"%","size":100,"sizes":[]},"_background_hover_gradient_angle":{"unit":"deg","size":180,"sizes":[]},"_background_hover_xpos":{"unit":"px","size":0,"sizes":[]},"_background_hover_xpos_tablet":{"unit":"px","size":0,"sizes":[]},"_background_hover_xpos_mobile":{"unit":"px","size":0,"sizes":[]},"_background_hover_ypos":{"unit":"px","size":0,"sizes":[]},"_background_hover_ypos_tablet":{"unit":"px","size":0,"sizes":[]},"_background_hover_ypos_mobile":{"unit":"px","size":0,"sizes":[]},"_background_hover_bg_width":{"unit":"%","size":100,"sizes":[]},"_background_hover_bg_width_tablet":{"unit":"px","size":"","sizes":[]},"_background_hover_bg_width_mobile":{"unit":"px","size":"","sizes":[]},"_background_hover_transition":{"unit":"px","size":"","sizes":[]},"_border_hover_transition":{"unit":"px","size":"","sizes":[]},"_element_custom_width":{"unit":"px","size":"","sizes":[]},"_element_custom_width_tablet":{"unit":"px","size":"","sizes":[]},"_element_custom_width_mobile":{"unit":"px","size":"","sizes":[]},"_offset_x":{"unit":"px","size":"0","sizes":[]},"_offset_x_tablet":{"unit":"px","size":"","sizes":[]},"_offset_x_mobile":{"unit":"px","size":"","sizes":[]},"_offset_x_end":{"unit":"px","size":"0","sizes":[]},"_offset_x_end_tablet":{"unit":"px","size":"","sizes":[]},"_offset_x_end_mobile":{"unit":"px","size":"","sizes":[]},"_offset_y":{"unit":"px","size":"0","sizes":[]},"_offset_y_tablet":{"unit":"px","size":"","sizes":[]},"_offset_y_mobile":{"unit":"px","size":"","sizes":[]},"_offset_y_end":{"unit":"px","size":"0","sizes":[]},"_offset_y_end_tablet":{"unit":"px","size":"","sizes":[]},"_offset_y_end_mobile":{"unit":"px","size":"","sizes":[]}},"elements":[],"isInner":false,"widgetType":"alert","elType":"widget"},{"id":"6a30e90a","settings":{"wp":{"list_id":"1489cde6-d97e-11e8-a3c9-06b79b628af2","title":"Subscribe to our list","include_first_name_field":"false","include_last_name_field":"false","include_consent":"false","consent_message":"I consent to receiving your weekly  special offers via email.","redirect_on_success":"false","include_referral":"true","success_redirect_url":""},"_background_background":"classic","_background_color":"#0c0003","_background_color_stop":{"unit":"%","size":0,"sizes":[]},"_background_color_b":"#ffffff","_background_color_b_stop":{"unit":"%","size":100,"sizes":[]},"_background_gradient_angle":{"unit":"deg","size":180,"sizes":[]},"_background_xpos":{"unit":"px","size":0,"sizes":[]},"_background_xpos_tablet":{"unit":"px","size":0,"sizes":[]},"_background_xpos_mobile":{"unit":"px","size":0,"sizes":[]},"_background_ypos":{"unit":"px","size":0,"sizes":[]},"_background_ypos_tablet":{"unit":"px","size":0,"sizes":[]},"_background_ypos_mobile":{"unit":"px","size":0,"sizes":[]},"_background_bg_width":{"unit":"%","size":100,"sizes":[]},"_background_bg_width_tablet":{"unit":"px","size":"","sizes":[]},"_background_bg_width_mobile":{"unit":"px","size":"","sizes":[]},"_background_hover_color_stop":{"unit":"%","size":0,"sizes":[]},"_background_hover_color_b_stop":{"unit":"%","size":100,"sizes":[]},"_background_hover_gradient_angle":{"unit":"deg","size":180,"sizes":[]},"_background_hover_xpos":{"unit":"px","size":0,"sizes":[]},"_background_hover_xpos_tablet":{"unit":"px","size":0,"sizes":[]},"_background_hover_xpos_mobile":{"unit":"px","size":0,"sizes":[]},"_background_hover_ypos":{"unit":"px","size":0,"sizes":[]},"_background_hover_ypos_tablet":{"unit":"px","size":0,"sizes":[]},"_background_hover_ypos_mobile":{"unit":"px","size":0,"sizes":[]},"_background_hover_bg_width":{"unit":"%","size":100,"sizes":[]},"_background_hover_bg_width_tablet":{"unit":"px","size":"","sizes":[]},"_background_hover_bg_width_mobile":{"unit":"px","size":"","sizes":[]},"_background_hover_transition":{"unit":"px","size":"","sizes":[]},"_border_hover_transition":{"unit":"px","size":"","sizes":[]},"_element_custom_width":{"unit":"px","size":"","sizes":[]},"_element_custom_width_tablet":{"unit":"px","size":"","sizes":[]},"_element_custom_width_mobile":{"unit":"px","size":"","sizes":[]},"_offset_x":{"unit":"px","size":"0","sizes":[]},"_offset_x_tablet":{"unit":"px","size":"","sizes":[]},"_offset_x_mobile":{"unit":"px","size":"","sizes":[]},"_offset_x_end":{"unit":"px","size":"0","sizes":[]},"_offset_x_end_tablet":{"unit":"px","size":"","sizes":[]},"_offset_x_end_mobile":{"unit":"px","size":"","sizes":[]},"_offset_y":{"unit":"px","size":"0","sizes":[]},"_offset_y_tablet":{"unit":"px","size":"","sizes":[]},"_offset_y_mobile":{"unit":"px","size":"","sizes":[]},"_offset_y_end":{"unit":"px","size":"0","sizes":[]},"_offset_y_end_tablet":{"unit":"px","size":"","sizes":[]},"_offset_y_end_mobile":{"unit":"px","size":"","sizes":[]}},"elements":[],"isInner":false,"widgetType":"wp-widget-emailoctopus","elType":"widget"},{"id":"30bb0da9","settings":{"editor":"","typography_typography":"custom","align":"center","text_color":"#ffffff","typography_font_family":"Montserrat","typography_font_size":{"unit":"px","size":"","sizes":[]},"typography_font_size_tablet":{"unit":"px","size":"","sizes":[]},"typography_font_size_mobile":{"unit":"px","size":"","sizes":[]},"typography_line_height":{"unit":"em","size":"","sizes":[]},"typography_line_height_tablet":{"unit":"em","size":"","sizes":[]},"typography_line_height_mobile":{"unit":"em","size":"","sizes":[]},"typography_letter_spacing":{"unit":"px","size":"","sizes":[]},"typography_letter_spacing_tablet":{"unit":"px","size":"","sizes":[]},"typography_letter_spacing_mobile":{"unit":"px","size":"","sizes":[]},"column_gap":{"unit":"px","size":"","sizes":[]},"column_gap_tablet":{"unit":"px","size":"","sizes":[]},"column_gap_mobile":{"unit":"px","size":"","sizes":[]},"drop_cap_size":{"unit":"px","size":5,"sizes":[]},"drop_cap_space":{"unit":"px","size":10,"sizes":[]},"drop_cap_border_radius":{"unit":"%","size":"","sizes":[]},"drop_cap_typography_font_size":{"unit":"px","size":"","sizes":[]},"drop_cap_typography_font_size_tablet":{"unit":"px","size":"","sizes":[]},"drop_cap_typography_font_size_mobile":{"unit":"px","size":"","sizes":[]},"drop_cap_typography_line_height":{"unit":"em","size":"","sizes":[]},"drop_cap_typography_line_height_tablet":{"unit":"em","size":"","sizes":[]},"drop_cap_typography_line_height_mobile":{"unit":"em","size":"","sizes":[]},"_background_color_stop":{"unit":"%","size":0,"sizes":[]},"_background_color_b_stop":{"unit":"%","size":100,"sizes":[]},"_background_gradient_angle":{"unit":"deg","size":180,"sizes":[]},"_background_xpos":{"unit":"px","size":0,"sizes":[]},"_background_xpos_tablet":{"unit":"px","size":0,"sizes":[]},"_background_xpos_mobile":{"unit":"px","size":0,"sizes":[]},"_background_ypos":{"unit":"px","size":0,"sizes":[]},"_background_ypos_tablet":{"unit":"px","size":0,"sizes":[]},"_background_ypos_mobile":{"unit":"px","size":0,"sizes":[]},"_background_bg_width":{"unit":"%","size":100,"sizes":[]},"_background_bg_width_tablet":{"unit":"px","size":"","sizes":[]},"_background_bg_width_mobile":{"unit":"px","size":"","sizes":[]},"_background_hover_color_stop":{"unit":"%","size":0,"sizes":[]},"_background_hover_color_b_stop":{"unit":"%","size":100,"sizes":[]},"_background_hover_gradient_angle":{"unit":"deg","size":180,"sizes":[]},"_background_hover_xpos":{"unit":"px","size":0,"sizes":[]},"_background_hover_xpos_tablet":{"unit":"px","size":0,"sizes":[]},"_background_hover_xpos_mobile":{"unit":"px","size":0,"sizes":[]},"_background_hover_ypos":{"unit":"px","size":0,"sizes":[]},"_background_hover_ypos_tablet":{"unit":"px","size":0,"sizes":[]},"_background_hover_ypos_mobile":{"unit":"px","size":0,"sizes":[]},"_background_hover_bg_width":{"unit":"%","size":100,"sizes":[]},"_background_hover_bg_width_tablet":{"unit":"px","size":"","sizes":[]},"_background_hover_bg_width_mobile":{"unit":"px","size":"","sizes":[]},"_background_hover_transition":{"unit":"px","size":"","sizes":[]},"_border_hover_transition":{"unit":"px","size":"","sizes":[]},"_element_custom_width":{"unit":"px","size":"","sizes":[]},"_element_custom_width_tablet":{"unit":"px","size":"","sizes":[]},"_element_custom_width_mobile":{"unit":"px","size":"","sizes":[]},"_offset_x":{"unit":"px","size":"0","sizes":[]},"_offset_x_tablet":{"unit":"px","size":"","sizes":[]},"_offset_x_mobile":{"unit":"px","size":"","sizes":[]},"_offset_x_end":{"unit":"px","size":"0","sizes":[]},"_offset_x_end_tablet":{"unit":"px","size":"","sizes":[]},"_offset_x_end_mobile":{"unit":"px","size":"","sizes":[]},"_offset_y":{"unit":"px","size":"0","sizes":[]},"_offset_y_tablet":{"unit":"px","size":"","sizes":[]},"_offset_y_mobile":{"unit":"px","size":"","sizes":[]},"_offset_y_end":{"unit":"px","size":"0","sizes":[]},"_offset_y_end_tablet":{"unit":"px","size":"","sizes":[]},"_offset_y_end_mobile":{"unit":"px","size":"","sizes":[]}},"elements":[],"isInner":false,"widgetType":"text-editor","elType":"widget"}],"isInner":false,"elType":"column"}],"isInner":false,"elType":"section"},{"id":"340e2dd8","settings":{"content_width":{"unit":"px","size":900},"background_background":"classic","background_color":"#f4f4f4","background_color_b":"#2642D3","background_gradient_angle":{"unit":"deg","size":140},"background_overlay_background":"classic","background_overlay_color":"#ebb0e7","background_overlay_color_b":"#2642d3","background_overlay_gradient_angle":{"unit":"deg","size":260},"background_overlay_image":{"id":"16","url":"http:\/\/vbucks-free-generator.com\/wp-content\/uploads\/2018\/10\/Background-Digital.jpg"},"background_overlay_position":"center center","background_overlay_attachment":"fixed","background_overlay_opacity":{"unit":"px","size":0.02},"css_filters_blur":{"unit":"px","size":3.3},"overlay_blend_mode":"luminosity","border_width":{"unit":"px","top":"0","right":"30","bottom":"0","left":"30","isLinked":false},"border_color":"#ffffff","margin":{"unit":"px","top":"-70","right":0,"bottom":"-70","left":0,"isLinked":true},"padding":{"unit":"px","top":"050","right":"0","bottom":"50","left":"0","isLinked":false},"background_overlay_size":"cover","border_radius":{"unit":"px","top":"0","right":"0","bottom":"010","left":"010","isLinked":false},"padding_tablet":{"unit":"px","top":"40","right":"40","bottom":"40","left":"40","isLinked":true},"padding_mobile":{"unit":"px","top":"20","right":"20","bottom":"20","left":"20","isLinked":true},"custom_height":{"unit":"px","size":400,"sizes":[]},"custom_height_tablet":{"unit":"px","size":"","sizes":[]},"custom_height_mobile":{"unit":"px","size":"","sizes":[]},"background_color_stop":{"unit":"%","size":0,"sizes":[]},"background_color_b_stop":{"unit":"%","size":100,"sizes":[]},"background_xpos":{"unit":"px","size":0,"sizes":[]},"background_xpos_tablet":{"unit":"px","size":0,"sizes":[]},"background_xpos_mobile":{"unit":"px","size":0,"sizes":[]},"background_ypos":{"unit":"px","size":0,"sizes":[]},"background_ypos_tablet":{"unit":"px","size":0,"sizes":[]},"background_ypos_mobile":{"unit":"px","size":0,"sizes":[]},"background_bg_width":{"unit":"%","size":100,"sizes":[]},"background_bg_width_tablet":{"unit":"px","size":"","sizes":[]},"background_bg_width_mobile":{"unit":"px","size":"","sizes":[]},"background_hover_color_stop":{"unit":"%","size":0,"sizes":[]},"background_hover_color_b_stop":{"unit":"%","size":100,"sizes":[]},"background_hover_gradient_angle":{"unit":"deg","size":180,"sizes":[]},"background_hover_xpos":{"unit":"px","size":0,"sizes":[]},"background_hover_xpos_tablet":{"unit":"px","size":0,"sizes":[]},"background_hover_xpos_mobile":{"unit":"px","size":0,"sizes":[]},"background_hover_ypos":{"unit":"px","size":0,"sizes":[]},"background_hover_ypos_tablet":{"unit":"px","size":0,"sizes":[]},"background_hover_ypos_mobile":{"unit":"px","size":0,"sizes":[]},"background_hover_bg_width":{"unit":"%","size":100,"sizes":[]},"background_hover_bg_width_tablet":{"unit":"px","size":"","sizes":[]},"background_hover_bg_width_mobile":{"unit":"px","size":"","sizes":[]},"background_hover_transition":{"unit":"px","size":0.3,"sizes":[]},"background_overlay_color_stop":{"unit":"%","size":0,"sizes":[]},"background_overlay_color_b_stop":{"unit":"%","size":100,"sizes":[]},"background_overlay_xpos":{"unit":"px","size":0,"sizes":[]},"background_overlay_xpos_tablet":{"unit":"px","size":0,"sizes":[]},"background_overlay_xpos_mobile":{"unit":"px","size":0,"sizes":[]},"background_overlay_ypos":{"unit":"px","size":0,"sizes":[]},"background_overlay_ypos_tablet":{"unit":"px","size":0,"sizes":[]},"background_overlay_ypos_mobile":{"unit":"px","size":0,"sizes":[]},"background_overlay_bg_width":{"unit":"%","size":100,"sizes":[]},"background_overlay_bg_width_tablet":{"unit":"px","size":"","sizes":[]},"background_overlay_bg_width_mobile":{"unit":"px","size":"","sizes":[]},"css_filters_brightness":{"unit":"px","size":100,"sizes":[]},"css_filters_contrast":{"unit":"px","size":100,"sizes":[]},"css_filters_saturate":{"unit":"px","size":100,"sizes":[]},"css_filters_hue":{"unit":"px","size":0,"sizes":[]},"background_overlay_hover_color_stop":{"unit":"%","size":0,"sizes":[]},"background_overlay_hover_color_b_stop":{"unit":"%","size":100,"sizes":[]},"background_overlay_hover_gradient_angle":{"unit":"deg","size":180,"sizes":[]},"background_overlay_hover_xpos":{"unit":"px","size":0,"sizes":[]},"background_overlay_hover_xpos_tablet":{"unit":"px","size":0,"sizes":[]},"background_overlay_hover_xpos_mobile":{"unit":"px","size":0,"sizes":[]},"background_overlay_hover_ypos":{"unit":"px","size":0,"sizes":[]},"background_overlay_hover_ypos_tablet":{"unit":"px","size":0,"sizes":[]},"background_overlay_hover_ypos_mobile":{"unit":"px","size":0,"sizes":[]},"background_overlay_hover_bg_width":{"unit":"%","size":100,"sizes":[]},"background_overlay_hover_bg_width_tablet":{"unit":"px","size":"","sizes":[]},"background_overlay_hover_bg_width_mobile":{"unit":"px","size":"","sizes":[]},"background_overlay_hover_opacity":{"unit":"px","size":0.5,"sizes":[]},"css_filters_hover_blur":{"unit":"px","size":0,"sizes":[]},"css_filters_hover_brightness":{"unit":"px","size":100,"sizes":[]},"css_filters_hover_contrast":{"unit":"px","size":100,"sizes":[]},"css_filters_hover_saturate":{"unit":"px","size":100,"sizes":[]},"css_filters_hover_hue":{"unit":"px","size":0,"sizes":[]},"background_overlay_hover_transition":{"unit":"px","size":0.3,"sizes":[]},"border_hover_transition":{"unit":"px","size":0.3,"sizes":[]},"shape_divider_top_width":{"unit":"%","size":"","sizes":[]},"shape_divider_top_width_tablet":{"unit":"%","size":"","sizes":[]},"shape_divider_top_width_mobile":{"unit":"%","size":"","sizes":[]},"shape_divider_top_height":{"unit":"px","size":"","sizes":[]},"shape_divider_top_height_tablet":{"unit":"px","size":"","sizes":[]},"shape_divider_top_height_mobile":{"unit":"px","size":"","sizes":[]},"shape_divider_bottom_width":{"unit":"%","size":"","sizes":[]},"shape_divider_bottom_width_tablet":{"unit":"%","size":"","sizes":[]},"shape_divider_bottom_width_mobile":{"unit":"%","size":"","sizes":[]},"shape_divider_bottom_height":{"unit":"px","size":"","sizes":[]},"shape_divider_bottom_height_tablet":{"unit":"px","size":"","sizes":[]},"shape_divider_bottom_height_mobile":{"unit":"px","size":"","sizes":[]}},"elements":[{"id":"3dde1f17","settings":{"_column_size":100,"space_between_widgets":30,"background_color_stop":{"unit":"%","size":0,"sizes":[]},"background_color_b_stop":{"unit":"%","size":100,"sizes":[]},"background_gradient_angle":{"unit":"deg","size":180,"sizes":[]},"background_xpos":{"unit":"px","size":0,"sizes":[]},"background_xpos_tablet":{"unit":"px","size":0,"sizes":[]},"background_xpos_mobile":{"unit":"px","size":0,"sizes":[]},"background_ypos":{"unit":"px","size":0,"sizes":[]},"background_ypos_tablet":{"unit":"px","size":0,"sizes":[]},"background_ypos_mobile":{"unit":"px","size":0,"sizes":[]},"background_bg_width":{"unit":"%","size":100,"sizes":[]},"background_bg_width_tablet":{"unit":"px","size":"","sizes":[]},"background_bg_width_mobile":{"unit":"px","size":"","sizes":[]},"background_hover_color_stop":{"unit":"%","size":0,"sizes":[]},"background_hover_color_b_stop":{"unit":"%","size":100,"sizes":[]},"background_hover_gradient_angle":{"unit":"deg","size":180,"sizes":[]},"background_hover_xpos":{"unit":"px","size":0,"sizes":[]},"background_hover_xpos_tablet":{"unit":"px","size":0,"sizes":[]},"background_hover_xpos_mobile":{"unit":"px","size":0,"sizes":[]},"background_hover_ypos":{"unit":"px","size":0,"sizes":[]},"background_hover_ypos_tablet":{"unit":"px","size":0,"sizes":[]},"background_hover_ypos_mobile":{"unit":"px","size":0,"sizes":[]},"background_hover_bg_width":{"unit":"%","size":100,"sizes":[]},"background_hover_bg_width_tablet":{"unit":"px","size":"","sizes":[]},"background_hover_bg_width_mobile":{"unit":"px","size":"","sizes":[]},"background_hover_transition":{"unit":"px","size":0.3,"sizes":[]},"background_overlay_color_stop":{"unit":"%","size":0,"sizes":[]},"background_overlay_color_b_stop":{"unit":"%","size":100,"sizes":[]},"background_overlay_gradient_angle":{"unit":"deg","size":180,"sizes":[]},"background_overlay_xpos":{"unit":"px","size":0,"sizes":[]},"background_overlay_xpos_tablet":{"unit":"px","size":0,"sizes":[]},"background_overlay_xpos_mobile":{"unit":"px","size":0,"sizes":[]},"background_overlay_ypos":{"unit":"px","size":0,"sizes":[]},"background_overlay_ypos_tablet":{"unit":"px","size":0,"sizes":[]},"background_overlay_ypos_mobile":{"unit":"px","size":0,"sizes":[]},"background_overlay_bg_width":{"unit":"%","size":100,"sizes":[]},"background_overlay_bg_width_tablet":{"unit":"px","size":"","sizes":[]},"background_overlay_bg_width_mobile":{"unit":"px","size":"","sizes":[]},"background_overlay_opacity":{"unit":"px","size":0.5,"sizes":[]},"css_filters_blur":{"unit":"px","size":0,"sizes":[]},"css_filters_brightness":{"unit":"px","size":100,"sizes":[]},"css_filters_contrast":{"unit":"px","size":100,"sizes":[]},"css_filters_saturate":{"unit":"px","size":100,"sizes":[]},"css_filters_hue":{"unit":"px","size":0,"sizes":[]},"background_overlay_hover_color_stop":{"unit":"%","size":0,"sizes":[]},"background_overlay_hover_color_b_stop":{"unit":"%","size":100,"sizes":[]},"background_overlay_hover_gradient_angle":{"unit":"deg","size":180,"sizes":[]},"background_overlay_hover_xpos":{"unit":"px","size":0,"sizes":[]},"background_overlay_hover_xpos_tablet":{"unit":"px","size":0,"sizes":[]},"background_overlay_hover_xpos_mobile":{"unit":"px","size":0,"sizes":[]},"background_overlay_hover_ypos":{"unit":"px","size":0,"sizes":[]},"background_overlay_hover_ypos_tablet":{"unit":"px","size":0,"sizes":[]},"background_overlay_hover_ypos_mobile":{"unit":"px","size":0,"sizes":[]},"background_overlay_hover_bg_width":{"unit":"%","size":100,"sizes":[]},"background_overlay_hover_bg_width_tablet":{"unit":"px","size":"","sizes":[]},"background_overlay_hover_bg_width_mobile":{"unit":"px","size":"","sizes":[]},"background_overlay_hover_opacity":{"unit":"px","size":0.5,"sizes":[]},"css_filters_hover_blur":{"unit":"px","size":0,"sizes":[]},"css_filters_hover_brightness":{"unit":"px","size":100,"sizes":[]},"css_filters_hover_contrast":{"unit":"px","size":100,"sizes":[]},"css_filters_hover_saturate":{"unit":"px","size":100,"sizes":[]},"css_filters_hover_hue":{"unit":"px","size":0,"sizes":[]},"background_overlay_hover_transition":{"unit":"px","size":0.3,"sizes":[]},"border_hover_transition":{"unit":"px","size":0.3,"sizes":[]}},"elements":[{"id":"271f2b42","settings":{"title":"Today users","typography_number_font_size":{"unit":"px","size":"","sizes":[]},"typography_number_font_size_tablet":{"unit":"px","size":"","sizes":[]},"typography_number_font_size_mobile":{"unit":"px","size":"","sizes":[]},"typography_number_line_height":{"unit":"em","size":"","sizes":[]},"typography_number_line_height_tablet":{"unit":"em","size":"","sizes":[]},"typography_number_line_height_mobile":{"unit":"em","size":"","sizes":[]},"typography_number_letter_spacing":{"unit":"px","size":"","sizes":[]},"typography_number_letter_spacing_tablet":{"unit":"px","size":"","sizes":[]},"typography_number_letter_spacing_mobile":{"unit":"px","size":"","sizes":[]},"typography_title_font_size":{"unit":"px","size":"","sizes":[]},"typography_title_font_size_tablet":{"unit":"px","size":"","sizes":[]},"typography_title_font_size_mobile":{"unit":"px","size":"","sizes":[]},"typography_title_line_height":{"unit":"em","size":"","sizes":[]},"typography_title_line_height_tablet":{"unit":"em","size":"","sizes":[]},"typography_title_line_height_mobile":{"unit":"em","size":"","sizes":[]},"typography_title_letter_spacing":{"unit":"px","size":"","sizes":[]},"typography_title_letter_spacing_tablet":{"unit":"px","size":"","sizes":[]},"typography_title_letter_spacing_mobile":{"unit":"px","size":"","sizes":[]},"_background_color_stop":{"unit":"%","size":0,"sizes":[]},"_background_color_b_stop":{"unit":"%","size":100,"sizes":[]},"_background_gradient_angle":{"unit":"deg","size":180,"sizes":[]},"_background_xpos":{"unit":"px","size":0,"sizes":[]},"_background_xpos_tablet":{"unit":"px","size":0,"sizes":[]},"_background_xpos_mobile":{"unit":"px","size":0,"sizes":[]},"_background_ypos":{"unit":"px","size":0,"sizes":[]},"_background_ypos_tablet":{"unit":"px","size":0,"sizes":[]},"_background_ypos_mobile":{"unit":"px","size":0,"sizes":[]},"_background_bg_width":{"unit":"%","size":100,"sizes":[]},"_background_bg_width_tablet":{"unit":"px","size":"","sizes":[]},"_background_bg_width_mobile":{"unit":"px","size":"","sizes":[]},"_background_hover_color_stop":{"unit":"%","size":0,"sizes":[]},"_background_hover_color_b_stop":{"unit":"%","size":100,"sizes":[]},"_background_hover_gradient_angle":{"unit":"deg","size":180,"sizes":[]},"_background_hover_xpos":{"unit":"px","size":0,"sizes":[]},"_background_hover_xpos_tablet":{"unit":"px","size":0,"sizes":[]},"_background_hover_xpos_mobile":{"unit":"px","size":0,"sizes":[]},"_background_hover_ypos":{"unit":"px","size":0,"sizes":[]},"_background_hover_ypos_tablet":{"unit":"px","size":0,"sizes":[]},"_background_hover_ypos_mobile":{"unit":"px","size":0,"sizes":[]},"_background_hover_bg_width":{"unit":"%","size":100,"sizes":[]},"_background_hover_bg_width_tablet":{"unit":"px","size":"","sizes":[]},"_background_hover_bg_width_mobile":{"unit":"px","size":"","sizes":[]},"_background_hover_transition":{"unit":"px","size":"","sizes":[]},"_border_hover_transition":{"unit":"px","size":"","sizes":[]},"_element_custom_width":{"unit":"px","size":"","sizes":[]},"_element_custom_width_tablet":{"unit":"px","size":"","sizes":[]},"_element_custom_width_mobile":{"unit":"px","size":"","sizes":[]},"_offset_x":{"unit":"px","size":"0","sizes":[]},"_offset_x_tablet":{"unit":"px","size":"","sizes":[]},"_offset_x_mobile":{"unit":"px","size":"","sizes":[]},"_offset_x_end":{"unit":"px","size":"0","sizes":[]},"_offset_x_end_tablet":{"unit":"px","size":"","sizes":[]},"_offset_x_end_mobile":{"unit":"px","size":"","sizes":[]},"_offset_y":{"unit":"px","size":"0","sizes":[]},"_offset_y_tablet":{"unit":"px","size":"","sizes":[]},"_offset_y_mobile":{"unit":"px","size":"","sizes":[]},"_offset_y_end":{"unit":"px","size":"0","sizes":[]},"_offset_y_end_tablet":{"unit":"px","size":"","sizes":[]},"_offset_y_end_mobile":{"unit":"px","size":"","sizes":[]}},"elements":[],"isInner":false,"widgetType":"counter","elType":"widget"}],"isInner":false,"elType":"column"}],"isInner":false,"elType":"section"},{"id":"48040494","settings":{"content_width":{"unit":"px","size":800},"background_background":"classic","background_color":"#e50914","background_color_b":"#e829db","background_gradient_angle":{"unit":"deg","size":210},"background_overlay_background":"classic","background_overlay_color":"#ebb0e7","background_overlay_color_b":"#2642d3","background_overlay_gradient_angle":{"unit":"deg","size":260},"background_overlay_image":{"id":16,"url":"http:\/\/box5694.temp.domains\/~vbucksfr\/wp-content\/uploads\/2018\/10\/Background-Digital.jpg"},"background_overlay_position":"top center","background_overlay_attachment":"fixed","background_overlay_opacity":{"unit":"px","size":0.03},"css_filters_blur":{"unit":"px","size":3.3},"overlay_blend_mode":"luminosity","border_width":{"unit":"px","top":"0","right":"30","bottom":"0","left":"30","isLinked":false},"border_color":"#ffffff","shape_divider_bottom_color":"#f4f4f4","margin":{"unit":"px","top":"50","right":0,"bottom":"0","left":0,"isLinked":false},"padding":{"unit":"px","top":"70","right":"0","bottom":"70","left":"0","isLinked":false},"background_overlay_repeat":"no-repeat","background_overlay_size":"cover","border_radius":{"unit":"px","top":"010","right":"010","bottom":"0","left":"0","isLinked":false},"padding_tablet":{"unit":"px","top":"50","right":"40","bottom":"50","left":"40","isLinked":false},"padding_mobile":{"unit":"px","top":"40","right":"20","bottom":"40","left":"20","isLinked":false},"custom_height":{"unit":"px","size":400,"sizes":[]},"custom_height_tablet":{"unit":"px","size":"","sizes":[]},"custom_height_mobile":{"unit":"px","size":"","sizes":[]},"background_color_stop":{"unit":"%","size":0,"sizes":[]},"background_color_b_stop":{"unit":"%","size":100,"sizes":[]},"background_xpos":{"unit":"px","size":0,"sizes":[]},"background_xpos_tablet":{"unit":"px","size":0,"sizes":[]},"background_xpos_mobile":{"unit":"px","size":0,"sizes":[]},"background_ypos":{"unit":"px","size":0,"sizes":[]},"background_ypos_tablet":{"unit":"px","size":0,"sizes":[]},"background_ypos_mobile":{"unit":"px","size":0,"sizes":[]},"background_bg_width":{"unit":"%","size":100,"sizes":[]},"background_bg_width_tablet":{"unit":"px","size":"","sizes":[]},"background_bg_width_mobile":{"unit":"px","size":"","sizes":[]},"background_hover_color_stop":{"unit":"%","size":0,"sizes":[]},"background_hover_color_b_stop":{"unit":"%","size":100,"sizes":[]},"background_hover_gradient_angle":{"unit":"deg","size":180,"sizes":[]},"background_hover_xpos":{"unit":"px","size":0,"sizes":[]},"background_hover_xpos_tablet":{"unit":"px","size":0,"sizes":[]},"background_hover_xpos_mobile":{"unit":"px","size":0,"sizes":[]},"background_hover_ypos":{"unit":"px","size":0,"sizes":[]},"background_hover_ypos_tablet":{"unit":"px","size":0,"sizes":[]},"background_hover_ypos_mobile":{"unit":"px","size":0,"sizes":[]},"background_hover_bg_width":{"unit":"%","size":100,"sizes":[]},"background_hover_bg_width_tablet":{"unit":"px","size":"","sizes":[]},"background_hover_bg_width_mobile":{"unit":"px","size":"","sizes":[]},"background_hover_transition":{"unit":"px","size":0.3,"sizes":[]},"background_overlay_color_stop":{"unit":"%","size":0,"sizes":[]},"background_overlay_color_b_stop":{"unit":"%","size":100,"sizes":[]},"background_overlay_xpos":{"unit":"px","size":0,"sizes":[]},"background_overlay_xpos_tablet":{"unit":"px","size":0,"sizes":[]},"background_overlay_xpos_mobile":{"unit":"px","size":0,"sizes":[]},"background_overlay_ypos":{"unit":"px","size":0,"sizes":[]},"background_overlay_ypos_tablet":{"unit":"px","size":0,"sizes":[]},"background_overlay_ypos_mobile":{"unit":"px","size":0,"sizes":[]},"background_overlay_bg_width":{"unit":"%","size":100,"sizes":[]},"background_overlay_bg_width_tablet":{"unit":"px","size":"","sizes":[]},"background_overlay_bg_width_mobile":{"unit":"px","size":"","sizes":[]},"css_filters_brightness":{"unit":"px","size":100,"sizes":[]},"css_filters_contrast":{"unit":"px","size":100,"sizes":[]},"css_filters_saturate":{"unit":"px","size":100,"sizes":[]},"css_filters_hue":{"unit":"px","size":0,"sizes":[]},"background_overlay_hover_color_stop":{"unit":"%","size":0,"sizes":[]},"background_overlay_hover_color_b_stop":{"unit":"%","size":100,"sizes":[]},"background_overlay_hover_gradient_angle":{"unit":"deg","size":180,"sizes":[]},"background_overlay_hover_xpos":{"unit":"px","size":0,"sizes":[]},"background_overlay_hover_xpos_tablet":{"unit":"px","size":0,"sizes":[]},"background_overlay_hover_xpos_mobile":{"unit":"px","size":0,"sizes":[]},"background_overlay_hover_ypos":{"unit":"px","size":0,"sizes":[]},"background_overlay_hover_ypos_tablet":{"unit":"px","size":0,"sizes":[]},"background_overlay_hover_ypos_mobile":{"unit":"px","size":0,"sizes":[]},"background_overlay_hover_bg_width":{"unit":"%","size":100,"sizes":[]},"background_overlay_hover_bg_width_tablet":{"unit":"px","size":"","sizes":[]},"background_overlay_hover_bg_width_mobile":{"unit":"px","size":"","sizes":[]},"background_overlay_hover_opacity":{"unit":"px","size":0.5,"sizes":[]},"css_filters_hover_blur":{"unit":"px","size":0,"sizes":[]},"css_filters_hover_brightness":{"unit":"px","size":100,"sizes":[]},"css_filters_hover_contrast":{"unit":"px","size":100,"sizes":[]},"css_filters_hover_saturate":{"unit":"px","size":100,"sizes":[]},"css_filters_hover_hue":{"unit":"px","size":0,"sizes":[]},"background_overlay_hover_transition":{"unit":"px","size":0.3,"sizes":[]},"border_hover_transition":{"unit":"px","size":0.3,"sizes":[]},"shape_divider_top_width":{"unit":"%","size":"","sizes":[]},"shape_divider_top_width_tablet":{"unit":"%","size":"","sizes":[]},"shape_divider_top_width_mobile":{"unit":"%","size":"","sizes":[]},"shape_divider_top_height":{"unit":"px","size":"","sizes":[]},"shape_divider_top_height_tablet":{"unit":"px","size":"","sizes":[]},"shape_divider_top_height_mobile":{"unit":"px","size":"","sizes":[]},"shape_divider_bottom_width":{"unit":"%","size":"","sizes":[]},"shape_divider_bottom_width_tablet":{"unit":"%","size":"","sizes":[]},"shape_divider_bottom_width_mobile":{"unit":"%","size":"","sizes":[]},"shape_divider_bottom_height":{"unit":"px","size":"","sizes":[]},"shape_divider_bottom_height_tablet":{"unit":"px","size":"","sizes":[]},"shape_divider_bottom_height_mobile":{"unit":"px","size":"","sizes":[]}},"elements":[{"id":"5c0a7f0e","settings":{"_column_size":100,"space_between_widgets":30,"background_color_stop":{"unit":"%","size":0,"sizes":[]},"background_color_b_stop":{"unit":"%","size":100,"sizes":[]},"background_gradient_angle":{"unit":"deg","size":180,"sizes":[]},"background_xpos":{"unit":"px","size":0,"sizes":[]},"background_xpos_tablet":{"unit":"px","size":0,"sizes":[]},"background_xpos_mobile":{"unit":"px","size":0,"sizes":[]},"background_ypos":{"unit":"px","size":0,"sizes":[]},"background_ypos_tablet":{"unit":"px","size":0,"sizes":[]},"background_ypos_mobile":{"unit":"px","size":0,"sizes":[]},"background_bg_width":{"unit":"%","size":100,"sizes":[]},"background_bg_width_tablet":{"unit":"px","size":"","sizes":[]},"background_bg_width_mobile":{"unit":"px","size":"","sizes":[]},"background_hover_color_stop":{"unit":"%","size":0,"sizes":[]},"background_hover_color_b_stop":{"unit":"%","size":100,"sizes":[]},"background_hover_gradient_angle":{"unit":"deg","size":180,"sizes":[]},"background_hover_xpos":{"unit":"px","size":0,"sizes":[]},"background_hover_xpos_tablet":{"unit":"px","size":0,"sizes":[]},"background_hover_xpos_mobile":{"unit":"px","size":0,"sizes":[]},"background_hover_ypos":{"unit":"px","size":0,"sizes":[]},"background_hover_ypos_tablet":{"unit":"px","size":0,"sizes":[]},"background_hover_ypos_mobile":{"unit":"px","size":0,"sizes":[]},"background_hover_bg_width":{"unit":"%","size":100,"sizes":[]},"background_hover_bg_width_tablet":{"unit":"px","size":"","sizes":[]},"background_hover_bg_width_mobile":{"unit":"px","size":"","sizes":[]},"background_hover_transition":{"unit":"px","size":0.3,"sizes":[]},"background_overlay_color_stop":{"unit":"%","size":0,"sizes":[]},"background_overlay_color_b_stop":{"unit":"%","size":100,"sizes":[]},"background_overlay_gradient_angle":{"unit":"deg","size":180,"sizes":[]},"background_overlay_xpos":{"unit":"px","size":0,"sizes":[]},"background_overlay_xpos_tablet":{"unit":"px","size":0,"sizes":[]},"background_overlay_xpos_mobile":{"unit":"px","size":0,"sizes":[]},"background_overlay_ypos":{"unit":"px","size":0,"sizes":[]},"background_overlay_ypos_tablet":{"unit":"px","size":0,"sizes":[]},"background_overlay_ypos_mobile":{"unit":"px","size":0,"sizes":[]},"background_overlay_bg_width":{"unit":"%","size":100,"sizes":[]},"background_overlay_bg_width_tablet":{"unit":"px","size":"","sizes":[]},"background_overlay_bg_width_mobile":{"unit":"px","size":"","sizes":[]},"background_overlay_opacity":{"unit":"px","size":0.5,"sizes":[]},"css_filters_blur":{"unit":"px","size":0,"sizes":[]},"css_filters_brightness":{"unit":"px","size":100,"sizes":[]},"css_filters_contrast":{"unit":"px","size":100,"sizes":[]},"css_filters_saturate":{"unit":"px","size":100,"sizes":[]},"css_filters_hue":{"unit":"px","size":0,"sizes":[]},"background_overlay_hover_color_stop":{"unit":"%","size":0,"sizes":[]},"background_overlay_hover_color_b_stop":{"unit":"%","size":100,"sizes":[]},"background_overlay_hover_gradient_angle":{"unit":"deg","size":180,"sizes":[]},"background_overlay_hover_xpos":{"unit":"px","size":0,"sizes":[]},"background_overlay_hover_xpos_tablet":{"unit":"px","size":0,"sizes":[]},"background_overlay_hover_xpos_mobile":{"unit":"px","size":0,"sizes":[]},"background_overlay_hover_ypos":{"unit":"px","size":0,"sizes":[]},"background_overlay_hover_ypos_tablet":{"unit":"px","size":0,"sizes":[]},"background_overlay_hover_ypos_mobile":{"unit":"px","size":0,"sizes":[]},"background_overlay_hover_bg_width":{"unit":"%","size":100,"sizes":[]},"background_overlay_hover_bg_width_tablet":{"unit":"px","size":"","sizes":[]},"background_overlay_hover_bg_width_mobile":{"unit":"px","size":"","sizes":[]},"background_overlay_hover_opacity":{"unit":"px","size":0.5,"sizes":[]},"css_filters_hover_blur":{"unit":"px","size":0,"sizes":[]},"css_filters_hover_brightness":{"unit":"px","size":100,"sizes":[]},"css_filters_hover_contrast":{"unit":"px","size":100,"sizes":[]},"css_filters_hover_saturate":{"unit":"px","size":100,"sizes":[]},"css_filters_hover_hue":{"unit":"px","size":0,"sizes":[]},"background_overlay_hover_transition":{"unit":"px","size":0.3,"sizes":[]},"border_hover_transition":{"unit":"px","size":0.3,"sizes":[]}},"elements":[{"id":"65713d39","settings":{"title":"<b>Free NETFLIX Account generator<\/b>","typography_typography":"custom","typography_font_size":{"unit":"px","size":50},"typography_font_weight":"300","typography_line_height":{"unit":"em","size":1.1},"align":"center","title_color":"#ffffff","typography_text_transform":"capitalize","text_shadow_text_shadow_type":"yes","text_shadow_text_shadow":{"horizontal":10,"vertical":10,"blur":20,"color":"rgba(0,0,0,0.11)"},"typography_font_family":"Montserrat","typography_font_size_tablet":{"unit":"px","size":"","sizes":[]},"typography_font_size_mobile":{"unit":"px","size":"","sizes":[]},"typography_line_height_tablet":{"unit":"em","size":"","sizes":[]},"typography_line_height_mobile":{"unit":"em","size":"","sizes":[]},"typography_letter_spacing":{"unit":"px","size":"","sizes":[]},"typography_letter_spacing_tablet":{"unit":"px","size":"","sizes":[]},"typography_letter_spacing_mobile":{"unit":"px","size":"","sizes":[]},"_background_color_stop":{"unit":"%","size":0,"sizes":[]},"_background_color_b_stop":{"unit":"%","size":100,"sizes":[]},"_background_gradient_angle":{"unit":"deg","size":180,"sizes":[]},"_background_xpos":{"unit":"px","size":0,"sizes":[]},"_background_xpos_tablet":{"unit":"px","size":0,"sizes":[]},"_background_xpos_mobile":{"unit":"px","size":0,"sizes":[]},"_background_ypos":{"unit":"px","size":0,"sizes":[]},"_background_ypos_tablet":{"unit":"px","size":0,"sizes":[]},"_background_ypos_mobile":{"unit":"px","size":0,"sizes":[]},"_background_bg_width":{"unit":"%","size":100,"sizes":[]},"_background_bg_width_tablet":{"unit":"px","size":"","sizes":[]},"_background_bg_width_mobile":{"unit":"px","size":"","sizes":[]},"_background_hover_color_stop":{"unit":"%","size":0,"sizes":[]},"_background_hover_color_b_stop":{"unit":"%","size":100,"sizes":[]},"_background_hover_gradient_angle":{"unit":"deg","size":180,"sizes":[]},"_background_hover_xpos":{"unit":"px","size":0,"sizes":[]},"_background_hover_xpos_tablet":{"unit":"px","size":0,"sizes":[]},"_background_hover_xpos_mobile":{"unit":"px","size":0,"sizes":[]},"_background_hover_ypos":{"unit":"px","size":0,"sizes":[]},"_background_hover_ypos_tablet":{"unit":"px","size":0,"sizes":[]},"_background_hover_ypos_mobile":{"unit":"px","size":0,"sizes":[]},"_background_hover_bg_width":{"unit":"%","size":100,"sizes":[]},"_background_hover_bg_width_tablet":{"unit":"px","size":"","sizes":[]},"_background_hover_bg_width_mobile":{"unit":"px","size":"","sizes":[]},"_background_hover_transition":{"unit":"px","size":"","sizes":[]},"_border_hover_transition":{"unit":"px","size":"","sizes":[]},"_element_custom_width":{"unit":"px","size":"","sizes":[]},"_element_custom_width_tablet":{"unit":"px","size":"","sizes":[]},"_element_custom_width_mobile":{"unit":"px","size":"","sizes":[]},"_offset_x":{"unit":"px","size":"0","sizes":[]},"_offset_x_tablet":{"unit":"px","size":"","sizes":[]},"_offset_x_mobile":{"unit":"px","size":"","sizes":[]},"_offset_x_end":{"unit":"px","size":"0","sizes":[]},"_offset_x_end_tablet":{"unit":"px","size":"","sizes":[]},"_offset_x_end_mobile":{"unit":"px","size":"","sizes":[]},"_offset_y":{"unit":"px","size":"0","sizes":[]},"_offset_y_tablet":{"unit":"px","size":"","sizes":[]},"_offset_y_mobile":{"unit":"px","size":"","sizes":[]},"_offset_y_end":{"unit":"px","size":"0","sizes":[]},"_offset_y_end_tablet":{"unit":"px","size":"","sizes":[]},"_offset_y_end_mobile":{"unit":"px","size":"","sizes":[]}},"elements":[],"isInner":false,"widgetType":"heading","elType":"widget"}],"isInner":false,"elType":"column"}],"isInner":false,"elType":"section"},{"id":"437638f3","settings":{"margin":{"unit":"px","top":"1","right":0,"bottom":"1","left":0,"isLinked":true},"padding":{"unit":"px","top":"16","right":"16","bottom":"16","left":"16","isLinked":true},"content_width":{"unit":"px","size":"","sizes":[]},"custom_height":{"unit":"px","size":400,"sizes":[]},"custom_height_tablet":{"unit":"px","size":"","sizes":[]},"custom_height_mobile":{"unit":"px","size":"","sizes":[]},"background_color_stop":{"unit":"%","size":0,"sizes":[]},"background_color_b_stop":{"unit":"%","size":100,"sizes":[]},"background_gradient_angle":{"unit":"deg","size":180,"sizes":[]},"background_xpos":{"unit":"px","size":0,"sizes":[]},"background_xpos_tablet":{"unit":"px","size":0,"sizes":[]},"background_xpos_mobile":{"unit":"px","size":0,"sizes":[]},"background_ypos":{"unit":"px","size":0,"sizes":[]},"background_ypos_tablet":{"unit":"px","size":0,"sizes":[]},"background_ypos_mobile":{"unit":"px","size":0,"sizes":[]},"background_bg_width":{"unit":"%","size":100,"sizes":[]},"background_bg_width_tablet":{"unit":"px","size":"","sizes":[]},"background_bg_width_mobile":{"unit":"px","size":"","sizes":[]},"background_hover_color_stop":{"unit":"%","size":0,"sizes":[]},"background_hover_color_b_stop":{"unit":"%","size":100,"sizes":[]},"background_hover_gradient_angle":{"unit":"deg","size":180,"sizes":[]},"background_hover_xpos":{"unit":"px","size":0,"sizes":[]},"background_hover_xpos_tablet":{"unit":"px","size":0,"sizes":[]},"background_hover_xpos_mobile":{"unit":"px","size":0,"sizes":[]},"background_hover_ypos":{"unit":"px","size":0,"sizes":[]},"background_hover_ypos_tablet":{"unit":"px","size":0,"sizes":[]},"background_hover_ypos_mobile":{"unit":"px","size":0,"sizes":[]},"background_hover_bg_width":{"unit":"%","size":100,"sizes":[]},"background_hover_bg_width_tablet":{"unit":"px","size":"","sizes":[]},"background_hover_bg_width_mobile":{"unit":"px","size":"","sizes":[]},"background_hover_transition":{"unit":"px","size":0.3,"sizes":[]},"background_overlay_color_stop":{"unit":"%","size":0,"sizes":[]},"background_overlay_color_b_stop":{"unit":"%","size":100,"sizes":[]},"background_overlay_gradient_angle":{"unit":"deg","size":180,"sizes":[]},"background_overlay_xpos":{"unit":"px","size":0,"sizes":[]},"background_overlay_xpos_tablet":{"unit":"px","size":0,"sizes":[]},"background_overlay_xpos_mobile":{"unit":"px","size":0,"sizes":[]},"background_overlay_ypos":{"unit":"px","size":0,"sizes":[]},"background_overlay_ypos_tablet":{"unit":"px","size":0,"sizes":[]},"background_overlay_ypos_mobile":{"unit":"px","size":0,"sizes":[]},"background_overlay_bg_width":{"unit":"%","size":100,"sizes":[]},"background_overlay_bg_width_tablet":{"unit":"px","size":"","sizes":[]},"background_overlay_bg_width_mobile":{"unit":"px","size":"","sizes":[]},"background_overlay_opacity":{"unit":"px","size":0.5,"sizes":[]},"css_filters_blur":{"unit":"px","size":0,"sizes":[]},"css_filters_brightness":{"unit":"px","size":100,"sizes":[]},"css_filters_contrast":{"unit":"px","size":100,"sizes":[]},"css_filters_saturate":{"unit":"px","size":100,"sizes":[]},"css_filters_hue":{"unit":"px","size":0,"sizes":[]},"background_overlay_hover_color_stop":{"unit":"%","size":0,"sizes":[]},"background_overlay_hover_color_b_stop":{"unit":"%","size":100,"sizes":[]},"background_overlay_hover_gradient_angle":{"unit":"deg","size":180,"sizes":[]},"background_overlay_hover_xpos":{"unit":"px","size":0,"sizes":[]},"background_overlay_hover_xpos_tablet":{"unit":"px","size":0,"sizes":[]},"background_overlay_hover_xpos_mobile":{"unit":"px","size":0,"sizes":[]},"background_overlay_hover_ypos":{"unit":"px","size":0,"sizes":[]},"background_overlay_hover_ypos_tablet":{"unit":"px","size":0,"sizes":[]},"background_overlay_hover_ypos_mobile":{"unit":"px","size":0,"sizes":[]},"background_overlay_hover_bg_width":{"unit":"%","size":100,"sizes":[]},"background_overlay_hover_bg_width_tablet":{"unit":"px","size":"","sizes":[]},"background_overlay_hover_bg_width_mobile":{"unit":"px","size":"","sizes":[]},"background_overlay_hover_opacity":{"unit":"px","size":0.5,"sizes":[]},"css_filters_hover_blur":{"unit":"px","size":0,"sizes":[]},"css_filters_hover_brightness":{"unit":"px","size":100,"sizes":[]},"css_filters_hover_contrast":{"unit":"px","size":100,"sizes":[]},"css_filters_hover_saturate":{"unit":"px","size":100,"sizes":[]},"css_filters_hover_hue":{"unit":"px","size":0,"sizes":[]},"background_overlay_hover_transition":{"unit":"px","size":0.3,"sizes":[]},"border_hover_transition":{"unit":"px","size":0.3,"sizes":[]},"shape_divider_top_width":{"unit":"%","size":"","sizes":[]},"shape_divider_top_width_tablet":{"unit":"%","size":"","sizes":[]},"shape_divider_top_width_mobile":{"unit":"%","size":"","sizes":[]},"shape_divider_top_height":{"unit":"px","size":"","sizes":[]},"shape_divider_top_height_tablet":{"unit":"px","size":"","sizes":[]},"shape_divider_top_height_mobile":{"unit":"px","size":"","sizes":[]},"shape_divider_bottom_width":{"unit":"%","size":"","sizes":[]},"shape_divider_bottom_width_tablet":{"unit":"%","size":"","sizes":[]},"shape_divider_bottom_width_mobile":{"unit":"%","size":"","sizes":[]},"shape_divider_bottom_height":{"unit":"px","size":"","sizes":[]},"shape_divider_bottom_height_tablet":{"unit":"px","size":"","sizes":[]},"shape_divider_bottom_height_mobile":{"unit":"px","size":"","sizes":[]}},"elements":[{"id":"172119d0","settings":{"_column_size":100,"background_color_stop":{"unit":"%","size":0,"sizes":[]},"background_color_b_stop":{"unit":"%","size":100,"sizes":[]},"background_gradient_angle":{"unit":"deg","size":180,"sizes":[]},"background_xpos":{"unit":"px","size":0,"sizes":[]},"background_xpos_tablet":{"unit":"px","size":0,"sizes":[]},"background_xpos_mobile":{"unit":"px","size":0,"sizes":[]},"background_ypos":{"unit":"px","size":0,"sizes":[]},"background_ypos_tablet":{"unit":"px","size":0,"sizes":[]},"background_ypos_mobile":{"unit":"px","size":0,"sizes":[]},"background_bg_width":{"unit":"%","size":100,"sizes":[]},"background_bg_width_tablet":{"unit":"px","size":"","sizes":[]},"background_bg_width_mobile":{"unit":"px","size":"","sizes":[]},"background_hover_color_stop":{"unit":"%","size":0,"sizes":[]},"background_hover_color_b_stop":{"unit":"%","size":100,"sizes":[]},"background_hover_gradient_angle":{"unit":"deg","size":180,"sizes":[]},"background_hover_xpos":{"unit":"px","size":0,"sizes":[]},"background_hover_xpos_tablet":{"unit":"px","size":0,"sizes":[]},"background_hover_xpos_mobile":{"unit":"px","size":0,"sizes":[]},"background_hover_ypos":{"unit":"px","size":0,"sizes":[]},"background_hover_ypos_tablet":{"unit":"px","size":0,"sizes":[]},"background_hover_ypos_mobile":{"unit":"px","size":0,"sizes":[]},"background_hover_bg_width":{"unit":"%","size":100,"sizes":[]},"background_hover_bg_width_tablet":{"unit":"px","size":"","sizes":[]},"background_hover_bg_width_mobile":{"unit":"px","size":"","sizes":[]},"background_hover_transition":{"unit":"px","size":0.3,"sizes":[]},"background_overlay_color_stop":{"unit":"%","size":0,"sizes":[]},"background_overlay_color_b_stop":{"unit":"%","size":100,"sizes":[]},"background_overlay_gradient_angle":{"unit":"deg","size":180,"sizes":[]},"background_overlay_xpos":{"unit":"px","size":0,"sizes":[]},"background_overlay_xpos_tablet":{"unit":"px","size":0,"sizes":[]},"background_overlay_xpos_mobile":{"unit":"px","size":0,"sizes":[]},"background_overlay_ypos":{"unit":"px","size":0,"sizes":[]},"background_overlay_ypos_tablet":{"unit":"px","size":0,"sizes":[]},"background_overlay_ypos_mobile":{"unit":"px","size":0,"sizes":[]},"background_overlay_bg_width":{"unit":"%","size":100,"sizes":[]},"background_overlay_bg_width_tablet":{"unit":"px","size":"","sizes":[]},"background_overlay_bg_width_mobile":{"unit":"px","size":"","sizes":[]},"background_overlay_opacity":{"unit":"px","size":0.5,"sizes":[]},"css_filters_blur":{"unit":"px","size":0,"sizes":[]},"css_filters_brightness":{"unit":"px","size":100,"sizes":[]},"css_filters_contrast":{"unit":"px","size":100,"sizes":[]},"css_filters_saturate":{"unit":"px","size":100,"sizes":[]},"css_filters_hue":{"unit":"px","size":0,"sizes":[]},"background_overlay_hover_color_stop":{"unit":"%","size":0,"sizes":[]},"background_overlay_hover_color_b_stop":{"unit":"%","size":100,"sizes":[]},"background_overlay_hover_gradient_angle":{"unit":"deg","size":180,"sizes":[]},"background_overlay_hover_xpos":{"unit":"px","size":0,"sizes":[]},"background_overlay_hover_xpos_tablet":{"unit":"px","size":0,"sizes":[]},"background_overlay_hover_xpos_mobile":{"unit":"px","size":0,"sizes":[]},"background_overlay_hover_ypos":{"unit":"px","size":0,"sizes":[]},"background_overlay_hover_ypos_tablet":{"unit":"px","size":0,"sizes":[]},"background_overlay_hover_ypos_mobile":{"unit":"px","size":0,"sizes":[]},"background_overlay_hover_bg_width":{"unit":"%","size":100,"sizes":[]},"background_overlay_hover_bg_width_tablet":{"unit":"px","size":"","sizes":[]},"background_overlay_hover_bg_width_mobile":{"unit":"px","size":"","sizes":[]},"background_overlay_hover_opacity":{"unit":"px","size":0.5,"sizes":[]},"css_filters_hover_blur":{"unit":"px","size":0,"sizes":[]},"css_filters_hover_brightness":{"unit":"px","size":100,"sizes":[]},"css_filters_hover_contrast":{"unit":"px","size":100,"sizes":[]},"css_filters_hover_saturate":{"unit":"px","size":100,"sizes":[]},"css_filters_hover_hue":{"unit":"px","size":0,"sizes":[]},"background_overlay_hover_transition":{"unit":"px","size":0.3,"sizes":[]},"border_hover_transition":{"unit":"px","size":0.3,"sizes":[]}},"elements":[{"id":"50096c56","settings":{"title":"Advice from some users:","align":"center","title_color":"#000000","typography_font_size":{"unit":"px","size":"","sizes":[]},"typography_font_size_tablet":{"unit":"px","size":"","sizes":[]},"typography_font_size_mobile":{"unit":"px","size":"","sizes":[]},"typography_line_height":{"unit":"em","size":"","sizes":[]},"typography_line_height_tablet":{"unit":"em","size":"","sizes":[]},"typography_line_height_mobile":{"unit":"em","size":"","sizes":[]},"typography_letter_spacing":{"unit":"px","size":"","sizes":[]},"typography_letter_spacing_tablet":{"unit":"px","size":"","sizes":[]},"typography_letter_spacing_mobile":{"unit":"px","size":"","sizes":[]},"_background_color_stop":{"unit":"%","size":0,"sizes":[]},"_background_color_b_stop":{"unit":"%","size":100,"sizes":[]},"_background_gradient_angle":{"unit":"deg","size":180,"sizes":[]},"_background_xpos":{"unit":"px","size":0,"sizes":[]},"_background_xpos_tablet":{"unit":"px","size":0,"sizes":[]},"_background_xpos_mobile":{"unit":"px","size":0,"sizes":[]},"_background_ypos":{"unit":"px","size":0,"sizes":[]},"_background_ypos_tablet":{"unit":"px","size":0,"sizes":[]},"_background_ypos_mobile":{"unit":"px","size":0,"sizes":[]},"_background_bg_width":{"unit":"%","size":100,"sizes":[]},"_background_bg_width_tablet":{"unit":"px","size":"","sizes":[]},"_background_bg_width_mobile":{"unit":"px","size":"","sizes":[]},"_background_hover_color_stop":{"unit":"%","size":0,"sizes":[]},"_background_hover_color_b_stop":{"unit":"%","size":100,"sizes":[]},"_background_hover_gradient_angle":{"unit":"deg","size":180,"sizes":[]},"_background_hover_xpos":{"unit":"px","size":0,"sizes":[]},"_background_hover_xpos_tablet":{"unit":"px","size":0,"sizes":[]},"_background_hover_xpos_mobile":{"unit":"px","size":0,"sizes":[]},"_background_hover_ypos":{"unit":"px","size":0,"sizes":[]},"_background_hover_ypos_tablet":{"unit":"px","size":0,"sizes":[]},"_background_hover_ypos_mobile":{"unit":"px","size":0,"sizes":[]},"_background_hover_bg_width":{"unit":"%","size":100,"sizes":[]},"_background_hover_bg_width_tablet":{"unit":"px","size":"","sizes":[]},"_background_hover_bg_width_mobile":{"unit":"px","size":"","sizes":[]},"_background_hover_transition":{"unit":"px","size":"","sizes":[]},"_border_hover_transition":{"unit":"px","size":"","sizes":[]},"_element_custom_width":{"unit":"px","size":"","sizes":[]},"_element_custom_width_tablet":{"unit":"px","size":"","sizes":[]},"_element_custom_width_mobile":{"unit":"px","size":"","sizes":[]},"_offset_x":{"unit":"px","size":"0","sizes":[]},"_offset_x_tablet":{"unit":"px","size":"","sizes":[]},"_offset_x_mobile":{"unit":"px","size":"","sizes":[]},"_offset_x_end":{"unit":"px","size":"0","sizes":[]},"_offset_x_end_tablet":{"unit":"px","size":"","sizes":[]},"_offset_x_end_mobile":{"unit":"px","size":"","sizes":[]},"_offset_y":{"unit":"px","size":"0","sizes":[]},"_offset_y_tablet":{"unit":"px","size":"","sizes":[]},"_offset_y_mobile":{"unit":"px","size":"","sizes":[]},"_offset_y_end":{"unit":"px","size":"0","sizes":[]},"_offset_y_end_tablet":{"unit":"px","size":"","sizes":[]},"_offset_y_end_mobile":{"unit":"px","size":"","sizes":[]}},"elements":[],"isInner":false,"widgetType":"heading","elType":"widget"},{"id":"20c48faf","settings":{"weight":{"unit":"px","size":1,"sizes":[]},"width":{"unit":"%","size":100,"sizes":[]},"width_tablet":{"unit":"%","size":"","sizes":[]},"width_mobile":{"unit":"%","size":"","sizes":[]},"gap":{"unit":"px","size":15,"sizes":[]},"gap_tablet":{"unit":"px","size":"","sizes":[]},"gap_mobile":{"unit":"px","size":"","sizes":[]},"_background_color_stop":{"unit":"%","size":0,"sizes":[]},"_background_color_b_stop":{"unit":"%","size":100,"sizes":[]},"_background_gradient_angle":{"unit":"deg","size":180,"sizes":[]},"_background_xpos":{"unit":"px","size":0,"sizes":[]},"_background_xpos_tablet":{"unit":"px","size":0,"sizes":[]},"_background_xpos_mobile":{"unit":"px","size":0,"sizes":[]},"_background_ypos":{"unit":"px","size":0,"sizes":[]},"_background_ypos_tablet":{"unit":"px","size":0,"sizes":[]},"_background_ypos_mobile":{"unit":"px","size":0,"sizes":[]},"_background_bg_width":{"unit":"%","size":100,"sizes":[]},"_background_bg_width_tablet":{"unit":"px","size":"","sizes":[]},"_background_bg_width_mobile":{"unit":"px","size":"","sizes":[]},"_background_hover_color_stop":{"unit":"%","size":0,"sizes":[]},"_background_hover_color_b_stop":{"unit":"%","size":100,"sizes":[]},"_background_hover_gradient_angle":{"unit":"deg","size":180,"sizes":[]},"_background_hover_xpos":{"unit":"px","size":0,"sizes":[]},"_background_hover_xpos_tablet":{"unit":"px","size":0,"sizes":[]},"_background_hover_xpos_mobile":{"unit":"px","size":0,"sizes":[]},"_background_hover_ypos":{"unit":"px","size":0,"sizes":[]},"_background_hover_ypos_tablet":{"unit":"px","size":0,"sizes":[]},"_background_hover_ypos_mobile":{"unit":"px","size":0,"sizes":[]},"_background_hover_bg_width":{"unit":"%","size":100,"sizes":[]},"_background_hover_bg_width_tablet":{"unit":"px","size":"","sizes":[]},"_background_hover_bg_width_mobile":{"unit":"px","size":"","sizes":[]},"_background_hover_transition":{"unit":"px","size":"","sizes":[]},"_border_hover_transition":{"unit":"px","size":"","sizes":[]},"_element_custom_width":{"unit":"px","size":"","sizes":[]},"_element_custom_width_tablet":{"unit":"px","size":"","sizes":[]},"_element_custom_width_mobile":{"unit":"px","size":"","sizes":[]},"_offset_x":{"unit":"px","size":"0","sizes":[]},"_offset_x_tablet":{"unit":"px","size":"","sizes":[]},"_offset_x_mobile":{"unit":"px","size":"","sizes":[]},"_offset_x_end":{"unit":"px","size":"0","sizes":[]},"_offset_x_end_tablet":{"unit":"px","size":"","sizes":[]},"_offset_x_end_mobile":{"unit":"px","size":"","sizes":[]},"_offset_y":{"unit":"px","size":"0","sizes":[]},"_offset_y_tablet":{"unit":"px","size":"","sizes":[]},"_offset_y_mobile":{"unit":"px","size":"","sizes":[]},"_offset_y_end":{"unit":"px","size":"0","sizes":[]},"_offset_y_end_tablet":{"unit":"px","size":"","sizes":[]},"_offset_y_end_mobile":{"unit":"px","size":"","sizes":[]}},"elements":[],"isInner":false,"widgetType":"divider","elType":"widget"}],"isInner":false,"elType":"column"}],"isInner":false,"elType":"section"},{"id":"56a66426","settings":{"structure":"20","content_width":{"unit":"px","size":"","sizes":[]},"custom_height":{"unit":"px","size":400,"sizes":[]},"custom_height_tablet":{"unit":"px","size":"","sizes":[]},"custom_height_mobile":{"unit":"px","size":"","sizes":[]},"background_color_stop":{"unit":"%","size":0,"sizes":[]},"background_color_b_stop":{"unit":"%","size":100,"sizes":[]},"background_gradient_angle":{"unit":"deg","size":180,"sizes":[]},"background_xpos":{"unit":"px","size":0,"sizes":[]},"background_xpos_tablet":{"unit":"px","size":0,"sizes":[]},"background_xpos_mobile":{"unit":"px","size":0,"sizes":[]},"background_ypos":{"unit":"px","size":0,"sizes":[]},"background_ypos_tablet":{"unit":"px","size":0,"sizes":[]},"background_ypos_mobile":{"unit":"px","size":0,"sizes":[]},"background_bg_width":{"unit":"%","size":100,"sizes":[]},"background_bg_width_tablet":{"unit":"px","size":"","sizes":[]},"background_bg_width_mobile":{"unit":"px","size":"","sizes":[]},"background_hover_color_stop":{"unit":"%","size":0,"sizes":[]},"background_hover_color_b_stop":{"unit":"%","size":100,"sizes":[]},"background_hover_gradient_angle":{"unit":"deg","size":180,"sizes":[]},"background_hover_xpos":{"unit":"px","size":0,"sizes":[]},"background_hover_xpos_tablet":{"unit":"px","size":0,"sizes":[]},"background_hover_xpos_mobile":{"unit":"px","size":0,"sizes":[]},"background_hover_ypos":{"unit":"px","size":0,"sizes":[]},"background_hover_ypos_tablet":{"unit":"px","size":0,"sizes":[]},"background_hover_ypos_mobile":{"unit":"px","size":0,"sizes":[]},"background_hover_bg_width":{"unit":"%","size":100,"sizes":[]},"background_hover_bg_width_tablet":{"unit":"px","size":"","sizes":[]},"background_hover_bg_width_mobile":{"unit":"px","size":"","sizes":[]},"background_hover_transition":{"unit":"px","size":0.3,"sizes":[]},"background_overlay_color_stop":{"unit":"%","size":0,"sizes":[]},"background_overlay_color_b_stop":{"unit":"%","size":100,"sizes":[]},"background_overlay_gradient_angle":{"unit":"deg","size":180,"sizes":[]},"background_overlay_xpos":{"unit":"px","size":0,"sizes":[]},"background_overlay_xpos_tablet":{"unit":"px","size":0,"sizes":[]},"background_overlay_xpos_mobile":{"unit":"px","size":0,"sizes":[]},"background_overlay_ypos":{"unit":"px","size":0,"sizes":[]},"background_overlay_ypos_tablet":{"unit":"px","size":0,"sizes":[]},"background_overlay_ypos_mobile":{"unit":"px","size":0,"sizes":[]},"background_overlay_bg_width":{"unit":"%","size":100,"sizes":[]},"background_overlay_bg_width_tablet":{"unit":"px","size":"","sizes":[]},"background_overlay_bg_width_mobile":{"unit":"px","size":"","sizes":[]},"background_overlay_opacity":{"unit":"px","size":0.5,"sizes":[]},"css_filters_blur":{"unit":"px","size":0,"sizes":[]},"css_filters_brightness":{"unit":"px","size":100,"sizes":[]},"css_filters_contrast":{"unit":"px","size":100,"sizes":[]},"css_filters_saturate":{"unit":"px","size":100,"sizes":[]},"css_filters_hue":{"unit":"px","size":0,"sizes":[]},"background_overlay_hover_color_stop":{"unit":"%","size":0,"sizes":[]},"background_overlay_hover_color_b_stop":{"unit":"%","size":100,"sizes":[]},"background_overlay_hover_gradient_angle":{"unit":"deg","size":180,"sizes":[]},"background_overlay_hover_xpos":{"unit":"px","size":0,"sizes":[]},"background_overlay_hover_xpos_tablet":{"unit":"px","size":0,"sizes":[]},"background_overlay_hover_xpos_mobile":{"unit":"px","size":0,"sizes":[]},"background_overlay_hover_ypos":{"unit":"px","size":0,"sizes":[]},"background_overlay_hover_ypos_tablet":{"unit":"px","size":0,"sizes":[]},"background_overlay_hover_ypos_mobile":{"unit":"px","size":0,"sizes":[]},"background_overlay_hover_bg_width":{"unit":"%","size":100,"sizes":[]},"background_overlay_hover_bg_width_tablet":{"unit":"px","size":"","sizes":[]},"background_overlay_hover_bg_width_mobile":{"unit":"px","size":"","sizes":[]},"background_overlay_hover_opacity":{"unit":"px","size":0.5,"sizes":[]},"css_filters_hover_blur":{"unit":"px","size":0,"sizes":[]},"css_filters_hover_brightness":{"unit":"px","size":100,"sizes":[]},"css_filters_hover_contrast":{"unit":"px","size":100,"sizes":[]},"css_filters_hover_saturate":{"unit":"px","size":100,"sizes":[]},"css_filters_hover_hue":{"unit":"px","size":0,"sizes":[]},"background_overlay_hover_transition":{"unit":"px","size":0.3,"sizes":[]},"border_hover_transition":{"unit":"px","size":0.3,"sizes":[]},"shape_divider_top_width":{"unit":"%","size":"","sizes":[]},"shape_divider_top_width_tablet":{"unit":"%","size":"","sizes":[]},"shape_divider_top_width_mobile":{"unit":"%","size":"","sizes":[]},"shape_divider_top_height":{"unit":"px","size":"","sizes":[]},"shape_divider_top_height_tablet":{"unit":"px","size":"","sizes":[]},"shape_divider_top_height_mobile":{"unit":"px","size":"","sizes":[]},"shape_divider_bottom_width":{"unit":"%","size":"","sizes":[]},"shape_divider_bottom_width_tablet":{"unit":"%","size":"","sizes":[]},"shape_divider_bottom_width_mobile":{"unit":"%","size":"","sizes":[]},"shape_divider_bottom_height":{"unit":"px","size":"","sizes":[]},"shape_divider_bottom_height_tablet":{"unit":"px","size":"","sizes":[]},"shape_divider_bottom_height_mobile":{"unit":"px","size":"","sizes":[]}},"elements":[{"id":"82ee21f","settings":{"_column_size":50,"_inline_size":49.825,"background_color_stop":{"unit":"%","size":0,"sizes":[]},"background_color_b_stop":{"unit":"%","size":100,"sizes":[]},"background_gradient_angle":{"unit":"deg","size":180,"sizes":[]},"background_xpos":{"unit":"px","size":0,"sizes":[]},"background_xpos_tablet":{"unit":"px","size":0,"sizes":[]},"background_xpos_mobile":{"unit":"px","size":0,"sizes":[]},"background_ypos":{"unit":"px","size":0,"sizes":[]},"background_ypos_tablet":{"unit":"px","size":0,"sizes":[]},"background_ypos_mobile":{"unit":"px","size":0,"sizes":[]},"background_bg_width":{"unit":"%","size":100,"sizes":[]},"background_bg_width_tablet":{"unit":"px","size":"","sizes":[]},"background_bg_width_mobile":{"unit":"px","size":"","sizes":[]},"background_hover_color_stop":{"unit":"%","size":0,"sizes":[]},"background_hover_color_b_stop":{"unit":"%","size":100,"sizes":[]},"background_hover_gradient_angle":{"unit":"deg","size":180,"sizes":[]},"background_hover_xpos":{"unit":"px","size":0,"sizes":[]},"background_hover_xpos_tablet":{"unit":"px","size":0,"sizes":[]},"background_hover_xpos_mobile":{"unit":"px","size":0,"sizes":[]},"background_hover_ypos":{"unit":"px","size":0,"sizes":[]},"background_hover_ypos_tablet":{"unit":"px","size":0,"sizes":[]},"background_hover_ypos_mobile":{"unit":"px","size":0,"sizes":[]},"background_hover_bg_width":{"unit":"%","size":100,"sizes":[]},"background_hover_bg_width_tablet":{"unit":"px","size":"","sizes":[]},"background_hover_bg_width_mobile":{"unit":"px","size":"","sizes":[]},"background_hover_transition":{"unit":"px","size":0.3,"sizes":[]},"background_overlay_color_stop":{"unit":"%","size":0,"sizes":[]},"background_overlay_color_b_stop":{"unit":"%","size":100,"sizes":[]},"background_overlay_gradient_angle":{"unit":"deg","size":180,"sizes":[]},"background_overlay_xpos":{"unit":"px","size":0,"sizes":[]},"background_overlay_xpos_tablet":{"unit":"px","size":0,"sizes":[]},"background_overlay_xpos_mobile":{"unit":"px","size":0,"sizes":[]},"background_overlay_ypos":{"unit":"px","size":0,"sizes":[]},"background_overlay_ypos_tablet":{"unit":"px","size":0,"sizes":[]},"background_overlay_ypos_mobile":{"unit":"px","size":0,"sizes":[]},"background_overlay_bg_width":{"unit":"%","size":100,"sizes":[]},"background_overlay_bg_width_tablet":{"unit":"px","size":"","sizes":[]},"background_overlay_bg_width_mobile":{"unit":"px","size":"","sizes":[]},"background_overlay_opacity":{"unit":"px","size":0.5,"sizes":[]},"css_filters_blur":{"unit":"px","size":0,"sizes":[]},"css_filters_brightness":{"unit":"px","size":100,"sizes":[]},"css_filters_contrast":{"unit":"px","size":100,"sizes":[]},"css_filters_saturate":{"unit":"px","size":100,"sizes":[]},"css_filters_hue":{"unit":"px","size":0,"sizes":[]},"background_overlay_hover_color_stop":{"unit":"%","size":0,"sizes":[]},"background_overlay_hover_color_b_stop":{"unit":"%","size":100,"sizes":[]},"background_overlay_hover_gradient_angle":{"unit":"deg","size":180,"sizes":[]},"background_overlay_hover_xpos":{"unit":"px","size":0,"sizes":[]},"background_overlay_hover_xpos_tablet":{"unit":"px","size":0,"sizes":[]},"background_overlay_hover_xpos_mobile":{"unit":"px","size":0,"sizes":[]},"background_overlay_hover_ypos":{"unit":"px","size":0,"sizes":[]},"background_overlay_hover_ypos_tablet":{"unit":"px","size":0,"sizes":[]},"background_overlay_hover_ypos_mobile":{"unit":"px","size":0,"sizes":[]},"background_overlay_hover_bg_width":{"unit":"%","size":100,"sizes":[]},"background_overlay_hover_bg_width_tablet":{"unit":"px","size":"","sizes":[]},"background_overlay_hover_bg_width_mobile":{"unit":"px","size":"","sizes":[]},"background_overlay_hover_opacity":{"unit":"px","size":0.5,"sizes":[]},"css_filters_hover_blur":{"unit":"px","size":0,"sizes":[]},"css_filters_hover_brightness":{"unit":"px","size":100,"sizes":[]},"css_filters_hover_contrast":{"unit":"px","size":100,"sizes":[]},"css_filters_hover_saturate":{"unit":"px","size":100,"sizes":[]},"css_filters_hover_hue":{"unit":"px","size":0,"sizes":[]},"background_overlay_hover_transition":{"unit":"px","size":0.3,"sizes":[]},"border_hover_transition":{"unit":"px","size":0.3,"sizes":[]}},"elements":[{"id":"39c5aea0","settings":{"testimonial_content":"<span style=\"color: rgb(122, 122, 122); font-size: 16px; white-space: normal;\">At the first time, i thought it a fake generator like the other netflix generators because i didn't win any account from them.<\/span><br style=\"color: rgb(122, 122, 122); font-size: 16px; white-space: normal;\"><span style=\"color: rgb(122, 122, 122); font-size: 16px; white-space: normal;\">The problem was on time, this generator is available just for the first 100 every day.<\/span><br style=\"color: rgb(122, 122, 122); font-size: 16px; white-space: normal;\"><span style=\"font-weight: 700; color: rgb(122, 122, 122); font-size: 16px; white-space: normal;\">My advice:<\/span><span style=\"color: rgb(122, 122, 122); font-size: 16px; white-space: normal;\">&nbsp;Try to use this generator on the morning and subscribe on notifications to be the first one?<\/span>","testimonial_image":{"url":"","id":""},"testimonial_name":"<h4 style=\"margin-bottom: 16px; white-space: normal; text-align: center;\"><span style=\"color: rgb(51, 204, 204);\"><strong>Ethan Micher<\/strong><\/span><\/h4>","testimonial_job":"","content_content_color":"#e50914","_background_background":"gradient","_background_color_stop":{"unit":"%","size":33},"_background_color_b":"#e25226","content_typography_font_size":{"unit":"px","size":"","sizes":[]},"content_typography_font_size_tablet":{"unit":"px","size":"","sizes":[]},"content_typography_font_size_mobile":{"unit":"px","size":"","sizes":[]},"content_typography_line_height":{"unit":"em","size":"","sizes":[]},"content_typography_line_height_tablet":{"unit":"em","size":"","sizes":[]},"content_typography_line_height_mobile":{"unit":"em","size":"","sizes":[]},"content_typography_letter_spacing":{"unit":"px","size":"","sizes":[]},"content_typography_letter_spacing_tablet":{"unit":"px","size":"","sizes":[]},"content_typography_letter_spacing_mobile":{"unit":"px","size":"","sizes":[]},"image_size":{"unit":"px","size":"","sizes":[]},"name_typography_font_size":{"unit":"px","size":"","sizes":[]},"name_typography_font_size_tablet":{"unit":"px","size":"","sizes":[]},"name_typography_font_size_mobile":{"unit":"px","size":"","sizes":[]},"name_typography_line_height":{"unit":"em","size":"","sizes":[]},"name_typography_line_height_tablet":{"unit":"em","size":"","sizes":[]},"name_typography_line_height_mobile":{"unit":"em","size":"","sizes":[]},"name_typography_letter_spacing":{"unit":"px","size":"","sizes":[]},"name_typography_letter_spacing_tablet":{"unit":"px","size":"","sizes":[]},"name_typography_letter_spacing_mobile":{"unit":"px","size":"","sizes":[]},"job_typography_font_size":{"unit":"px","size":"","sizes":[]},"job_typography_font_size_tablet":{"unit":"px","size":"","sizes":[]},"job_typography_font_size_mobile":{"unit":"px","size":"","sizes":[]},"job_typography_line_height":{"unit":"em","size":"","sizes":[]},"job_typography_line_height_tablet":{"unit":"em","size":"","sizes":[]},"job_typography_line_height_mobile":{"unit":"em","size":"","sizes":[]},"job_typography_letter_spacing":{"unit":"px","size":"","sizes":[]},"job_typography_letter_spacing_tablet":{"unit":"px","size":"","sizes":[]},"job_typography_letter_spacing_mobile":{"unit":"px","size":"","sizes":[]},"_background_color_b_stop":{"unit":"%","size":100,"sizes":[]},"_background_gradient_angle":{"unit":"deg","size":180,"sizes":[]},"_background_xpos":{"unit":"px","size":0,"sizes":[]},"_background_xpos_tablet":{"unit":"px","size":0,"sizes":[]},"_background_xpos_mobile":{"unit":"px","size":0,"sizes":[]},"_background_ypos":{"unit":"px","size":0,"sizes":[]},"_background_ypos_tablet":{"unit":"px","size":0,"sizes":[]},"_background_ypos_mobile":{"unit":"px","size":0,"sizes":[]},"_background_bg_width":{"unit":"%","size":100,"sizes":[]},"_background_bg_width_tablet":{"unit":"px","size":"","sizes":[]},"_background_bg_width_mobile":{"unit":"px","size":"","sizes":[]},"_background_hover_color_stop":{"unit":"%","size":0,"sizes":[]},"_background_hover_color_b_stop":{"unit":"%","size":100,"sizes":[]},"_background_hover_gradient_angle":{"unit":"deg","size":180,"sizes":[]},"_background_hover_xpos":{"unit":"px","size":0,"sizes":[]},"_background_hover_xpos_tablet":{"unit":"px","size":0,"sizes":[]},"_background_hover_xpos_mobile":{"unit":"px","size":0,"sizes":[]},"_background_hover_ypos":{"unit":"px","size":0,"sizes":[]},"_background_hover_ypos_tablet":{"unit":"px","size":0,"sizes":[]},"_background_hover_ypos_mobile":{"unit":"px","size":0,"sizes":[]},"_background_hover_bg_width":{"unit":"%","size":100,"sizes":[]},"_background_hover_bg_width_tablet":{"unit":"px","size":"","sizes":[]},"_background_hover_bg_width_mobile":{"unit":"px","size":"","sizes":[]},"_background_hover_transition":{"unit":"px","size":"","sizes":[]},"_border_hover_transition":{"unit":"px","size":"","sizes":[]},"_element_custom_width":{"unit":"px","size":"","sizes":[]},"_element_custom_width_tablet":{"unit":"px","size":"","sizes":[]},"_element_custom_width_mobile":{"unit":"px","size":"","sizes":[]},"_offset_x":{"unit":"px","size":"0","sizes":[]},"_offset_x_tablet":{"unit":"px","size":"","sizes":[]},"_offset_x_mobile":{"unit":"px","size":"","sizes":[]},"_offset_x_end":{"unit":"px","size":"0","sizes":[]},"_offset_x_end_tablet":{"unit":"px","size":"","sizes":[]},"_offset_x_end_mobile":{"unit":"px","size":"","sizes":[]},"_offset_y":{"unit":"px","size":"0","sizes":[]},"_offset_y_tablet":{"unit":"px","size":"","sizes":[]},"_offset_y_mobile":{"unit":"px","size":"","sizes":[]},"_offset_y_end":{"unit":"px","size":"0","sizes":[]},"_offset_y_end_tablet":{"unit":"px","size":"","sizes":[]},"_offset_y_end_mobile":{"unit":"px","size":"","sizes":[]}},"elements":[],"isInner":false,"widgetType":"testimonial","elType":"widget"}],"isInner":false,"elType":"column"},{"id":"6d91413b","settings":{"_column_size":50,"_inline_size":50.175,"background_color_stop":{"unit":"%","size":0,"sizes":[]},"background_color_b_stop":{"unit":"%","size":100,"sizes":[]},"background_gradient_angle":{"unit":"deg","size":180,"sizes":[]},"background_xpos":{"unit":"px","size":0,"sizes":[]},"background_xpos_tablet":{"unit":"px","size":0,"sizes":[]},"background_xpos_mobile":{"unit":"px","size":0,"sizes":[]},"background_ypos":{"unit":"px","size":0,"sizes":[]},"background_ypos_tablet":{"unit":"px","size":0,"sizes":[]},"background_ypos_mobile":{"unit":"px","size":0,"sizes":[]},"background_bg_width":{"unit":"%","size":100,"sizes":[]},"background_bg_width_tablet":{"unit":"px","size":"","sizes":[]},"background_bg_width_mobile":{"unit":"px","size":"","sizes":[]},"background_hover_color_stop":{"unit":"%","size":0,"sizes":[]},"background_hover_color_b_stop":{"unit":"%","size":100,"sizes":[]},"background_hover_gradient_angle":{"unit":"deg","size":180,"sizes":[]},"background_hover_xpos":{"unit":"px","size":0,"sizes":[]},"background_hover_xpos_tablet":{"unit":"px","size":0,"sizes":[]},"background_hover_xpos_mobile":{"unit":"px","size":0,"sizes":[]},"background_hover_ypos":{"unit":"px","size":0,"sizes":[]},"background_hover_ypos_tablet":{"unit":"px","size":0,"sizes":[]},"background_hover_ypos_mobile":{"unit":"px","size":0,"sizes":[]},"background_hover_bg_width":{"unit":"%","size":100,"sizes":[]},"background_hover_bg_width_tablet":{"unit":"px","size":"","sizes":[]},"background_hover_bg_width_mobile":{"unit":"px","size":"","sizes":[]},"background_hover_transition":{"unit":"px","size":0.3,"sizes":[]},"background_overlay_color_stop":{"unit":"%","size":0,"sizes":[]},"background_overlay_color_b_stop":{"unit":"%","size":100,"sizes":[]},"background_overlay_gradient_angle":{"unit":"deg","size":180,"sizes":[]},"background_overlay_xpos":{"unit":"px","size":0,"sizes":[]},"background_overlay_xpos_tablet":{"unit":"px","size":0,"sizes":[]},"background_overlay_xpos_mobile":{"unit":"px","size":0,"sizes":[]},"background_overlay_ypos":{"unit":"px","size":0,"sizes":[]},"background_overlay_ypos_tablet":{"unit":"px","size":0,"sizes":[]},"background_overlay_ypos_mobile":{"unit":"px","size":0,"sizes":[]},"background_overlay_bg_width":{"unit":"%","size":100,"sizes":[]},"background_overlay_bg_width_tablet":{"unit":"px","size":"","sizes":[]},"background_overlay_bg_width_mobile":{"unit":"px","size":"","sizes":[]},"background_overlay_opacity":{"unit":"px","size":0.5,"sizes":[]},"css_filters_blur":{"unit":"px","size":0,"sizes":[]},"css_filters_brightness":{"unit":"px","size":100,"sizes":[]},"css_filters_contrast":{"unit":"px","size":100,"sizes":[]},"css_filters_saturate":{"unit":"px","size":100,"sizes":[]},"css_filters_hue":{"unit":"px","size":0,"sizes":[]},"background_overlay_hover_color_stop":{"unit":"%","size":0,"sizes":[]},"background_overlay_hover_color_b_stop":{"unit":"%","size":100,"sizes":[]},"background_overlay_hover_gradient_angle":{"unit":"deg","size":180,"sizes":[]},"background_overlay_hover_xpos":{"unit":"px","size":0,"sizes":[]},"background_overlay_hover_xpos_tablet":{"unit":"px","size":0,"sizes":[]},"background_overlay_hover_xpos_mobile":{"unit":"px","size":0,"sizes":[]},"background_overlay_hover_ypos":{"unit":"px","size":0,"sizes":[]},"background_overlay_hover_ypos_tablet":{"unit":"px","size":0,"sizes":[]},"background_overlay_hover_ypos_mobile":{"unit":"px","size":0,"sizes":[]},"background_overlay_hover_bg_width":{"unit":"%","size":100,"sizes":[]},"background_overlay_hover_bg_width_tablet":{"unit":"px","size":"","sizes":[]},"background_overlay_hover_bg_width_mobile":{"unit":"px","size":"","sizes":[]},"background_overlay_hover_opacity":{"unit":"px","size":0.5,"sizes":[]},"css_filters_hover_blur":{"unit":"px","size":0,"sizes":[]},"css_filters_hover_brightness":{"unit":"px","size":100,"sizes":[]},"css_filters_hover_contrast":{"unit":"px","size":100,"sizes":[]},"css_filters_hover_saturate":{"unit":"px","size":100,"sizes":[]},"css_filters_hover_hue":{"unit":"px","size":0,"sizes":[]},"background_overlay_hover_transition":{"unit":"px","size":0.3,"sizes":[]},"border_hover_transition":{"unit":"px","size":0.3,"sizes":[]}},"elements":[{"id":"5bcc8635","settings":{"testimonial_content":"<p style=\"color: rgb(122, 122, 122); font-size: 16px; white-space: normal;\">The best generator i used to earn free netflix accounts. Unfortunately after 5 days of trying!<\/p><p style=\"margin-bottom: 0px; color: rgb(122, 122, 122); font-size: 16px; white-space: normal;\"><strong>My advice:<\/strong>&nbsp;Sometimes more than 6 months doesn't work try to use 1 month it work very well!<span style=\"color: rgb(45, 26, 26); font-size: 1.3em; white-space: pre-wrap; background-color: transparent;\"><\/span><\/p>","testimonial_image":{"url":"","id":""},"testimonial_name":"<h4 style=\"margin-bottom: 16px; white-space: normal;\"><span style=\"color: rgb(51, 204, 204);\"><strong>Adam Kern<\/strong><\/span><\/h4>","testimonial_job":"","testimonial_image_position":"top","content_content_color":"#2d1a1a","content_typography_font_size":{"unit":"px","size":"","sizes":[]},"content_typography_font_size_tablet":{"unit":"px","size":"","sizes":[]},"content_typography_font_size_mobile":{"unit":"px","size":"","sizes":[]},"content_typography_line_height":{"unit":"em","size":"","sizes":[]},"content_typography_line_height_tablet":{"unit":"em","size":"","sizes":[]},"content_typography_line_height_mobile":{"unit":"em","size":"","sizes":[]},"content_typography_letter_spacing":{"unit":"px","size":"","sizes":[]},"content_typography_letter_spacing_tablet":{"unit":"px","size":"","sizes":[]},"content_typography_letter_spacing_mobile":{"unit":"px","size":"","sizes":[]},"image_size":{"unit":"px","size":"","sizes":[]},"name_typography_font_size":{"unit":"px","size":"","sizes":[]},"name_typography_font_size_tablet":{"unit":"px","size":"","sizes":[]},"name_typography_font_size_mobile":{"unit":"px","size":"","sizes":[]},"name_typography_line_height":{"unit":"em","size":"","sizes":[]},"name_typography_line_height_tablet":{"unit":"em","size":"","sizes":[]},"name_typography_line_height_mobile":{"unit":"em","size":"","sizes":[]},"name_typography_letter_spacing":{"unit":"px","size":"","sizes":[]},"name_typography_letter_spacing_tablet":{"unit":"px","size":"","sizes":[]},"name_typography_letter_spacing_mobile":{"unit":"px","size":"","sizes":[]},"job_typography_font_size":{"unit":"px","size":"","sizes":[]},"job_typography_font_size_tablet":{"unit":"px","size":"","sizes":[]},"job_typography_font_size_mobile":{"unit":"px","size":"","sizes":[]},"job_typography_line_height":{"unit":"em","size":"","sizes":[]},"job_typography_line_height_tablet":{"unit":"em","size":"","sizes":[]},"job_typography_line_height_mobile":{"unit":"em","size":"","sizes":[]},"job_typography_letter_spacing":{"unit":"px","size":"","sizes":[]},"job_typography_letter_spacing_tablet":{"unit":"px","size":"","sizes":[]},"job_typography_letter_spacing_mobile":{"unit":"px","size":"","sizes":[]},"_background_color_stop":{"unit":"%","size":0,"sizes":[]},"_background_color_b_stop":{"unit":"%","size":100,"sizes":[]},"_background_gradient_angle":{"unit":"deg","size":180,"sizes":[]},"_background_xpos":{"unit":"px","size":0,"sizes":[]},"_background_xpos_tablet":{"unit":"px","size":0,"sizes":[]},"_background_xpos_mobile":{"unit":"px","size":0,"sizes":[]},"_background_ypos":{"unit":"px","size":0,"sizes":[]},"_background_ypos_tablet":{"unit":"px","size":0,"sizes":[]},"_background_ypos_mobile":{"unit":"px","size":0,"sizes":[]},"_background_bg_width":{"unit":"%","size":100,"sizes":[]},"_background_bg_width_tablet":{"unit":"px","size":"","sizes":[]},"_background_bg_width_mobile":{"unit":"px","size":"","sizes":[]},"_background_hover_color_stop":{"unit":"%","size":0,"sizes":[]},"_background_hover_color_b_stop":{"unit":"%","size":100,"sizes":[]},"_background_hover_gradient_angle":{"unit":"deg","size":180,"sizes":[]},"_background_hover_xpos":{"unit":"px","size":0,"sizes":[]},"_background_hover_xpos_tablet":{"unit":"px","size":0,"sizes":[]},"_background_hover_xpos_mobile":{"unit":"px","size":0,"sizes":[]},"_background_hover_ypos":{"unit":"px","size":0,"sizes":[]},"_background_hover_ypos_tablet":{"unit":"px","size":0,"sizes":[]},"_background_hover_ypos_mobile":{"unit":"px","size":0,"sizes":[]},"_background_hover_bg_width":{"unit":"%","size":100,"sizes":[]},"_background_hover_bg_width_tablet":{"unit":"px","size":"","sizes":[]},"_background_hover_bg_width_mobile":{"unit":"px","size":"","sizes":[]},"_background_hover_transition":{"unit":"px","size":"","sizes":[]},"_border_hover_transition":{"unit":"px","size":"","sizes":[]},"_element_custom_width":{"unit":"px","size":"","sizes":[]},"_element_custom_width_tablet":{"unit":"px","size":"","sizes":[]},"_element_custom_width_mobile":{"unit":"px","size":"","sizes":[]},"_offset_x":{"unit":"px","size":"0","sizes":[]},"_offset_x_tablet":{"unit":"px","size":"","sizes":[]},"_offset_x_mobile":{"unit":"px","size":"","sizes":[]},"_offset_x_end":{"unit":"px","size":"0","sizes":[]},"_offset_x_end_tablet":{"unit":"px","size":"","sizes":[]},"_offset_x_end_mobile":{"unit":"px","size":"","sizes":[]},"_offset_y":{"unit":"px","size":"0","sizes":[]},"_offset_y_tablet":{"unit":"px","size":"","sizes":[]},"_offset_y_mobile":{"unit":"px","size":"","sizes":[]},"_offset_y_end":{"unit":"px","size":"0","sizes":[]},"_offset_y_end_tablet":{"unit":"px","size":"","sizes":[]},"_offset_y_end_mobile":{"unit":"px","size":"","sizes":[]}},"elements":[],"isInner":false,"widgetType":"testimonial","elType":"widget"}],"isInner":false,"elType":"column"}],"isInner":false,"elType":"section"}],"page_settings":{"background_background":"gradient","background_color_stop":{"unit":"%","size":0,"sizes":[]},"background_color_b":"#dd2553","background_color_b_stop":{"unit":"%","size":100,"sizes":[]},"background_gradient_angle":{"unit":"deg","size":180,"sizes":[]},"background_xpos":{"unit":"px","size":0,"sizes":[]},"background_xpos_tablet":{"unit":"px","size":0,"sizes":[]},"background_xpos_mobile":{"unit":"px","size":0,"sizes":[]},"background_ypos":{"unit":"px","size":0,"sizes":[]},"background_ypos_tablet":{"unit":"px","size":0,"sizes":[]},"background_ypos_mobile":{"unit":"px","size":0,"sizes":[]},"background_bg_width":{"unit":"%","size":100,"sizes":[]},"background_bg_width_tablet":{"unit":"px","size":"","sizes":[]},"background_bg_width_mobile":{"unit":"px","size":"","sizes":[]}}}